Workbook

Sheet PARAMETROS
A1: RENOVACION DE CONTRATOS FEE 2026 - PARAMETROS Y SUPUESTOS
A2: Universo de analisis: 76 contratos FEE (2026) - bolsas ZBB y Trade Spend combinadas. El presupuesto de cada escenario se evalua contra el total de los 76 clientes, priorizados por importancia (no por bolsa de origen).
A4: BOLSAS DE PRESUPUESTO PAGADAS EN 2026 (referencia historica, archivo original)
A5: Total pagado bolsa ZBB (30 contratos) | B5: 1101000000 | C5: Dato provisto por el usuario, verificado contra el archivo FEE_2026.xlsx.
A6: Total pagado bolsa Trade Spend (46 contratos) | B6: 679000000 | C6: Antes fuera de alcance; a pedido del usuario ahora se incluyen los 46 clientes en el ranking unico de priorizacion (misma importancia que ZBB).
A7: Total pagado ambas bolsas (76 contratos) | B7: 1780000000 | C7: Referencia. Verificado contra el archivo original (suma exacta).
A9: ESCENARIOS DE PRESUPUESTO DISPONIBLE (aplica sobre el universo completo de 76 contratos)
A10: Escenario 1 - Presupuesto disponible hoy (misma bolsa ZBB) | B10: 1430276270 | C10: Dato provisto por el usuario.
A11: Escenario 2 - Adicional a conseguir | B11: 219723730 | C11: Dato provisto por el usuario.
A12: Escenario 2 - Total teorico (Esc.1 + Adicional) | B12: =$B$10+B11
A13: Escenario 2 - Total CONFIRMADO a usar en el modelo | B13: 1650000000 | C13: VALOR USADO EN EL MODELO (celda editable). Ajustar si el numero correcto es otro.
A14: Escenario 3 - Presupuesto total disponible | B14: 2000000000 | C14: Dato provisto por el usuario.
A16: TABLA DE INFLACION ACUMULADA POR DURACION (fuente: hoja Hoja5 del archivo original)
A17: Duracion contrato (meses) | B17: Inflacion acumulada
A18: 12 | B18: 0.25
A19: 24 | B19: 0.68
A20: 36 | B20: 2.13
A21: Nota | C21: Para contratos con duracion intermedia (10, 21 meses), el archivo original aplico manualmente la tasa del tramo mas cercano (10m -> 12m; 21m -> 24m). Se replico igual criterio.
A23: CRITERIOS DE COSTO DE RENOVACION (3 referencias en paralelo)
A24: Criterio 1 - FEE Actualizado | C24: Valor de referencia de mercado/sistema tomado del archivo original (columna "FEE ACTUALIZADO"). Dato fijo: su formula original enlazaba a un archivo externo no disponible.
A25: Criterio 2 - FEE + Inflacion acumulada | C25: Formula: Monto FEE actual x (1 + Inflacion acumulada segun duracion).
A26: Criterio 3 - Punto medio (NUEVO) | C26: Formula: promedio simple entre el Monto FEE Actual (lo que se pago en su momento) y el Criterio 2 (FEE + inflacion). Sirve como referencia intermedia de negociacion. Supuesto: si el "punto medio" pedido era entre Criterio 1 y Criterio 2 en vez de Monto FEE y Criterio 2, avisar para ajustar la formula.
A28: PRIORIZACION Y ALCANCE
A29: 1) Los 76 contratos (ZBB + Trade Spend) se ordenan juntos por Tier (IMPERDIBLE > DISCUTIBLE > CERRO) y, dentro de cada tier, por Monto FEE actual descendente (proxy de importancia por defecto). La bolsa de origen (columna "Bolsa") es solo informativa/filtrable, no afecta el orden.
A30: 2) La columna "Prioridad" (hoja BASE) es editable: para cambiar el orden manual, escribir el numero deseado y reordenar las filas (Datos > Ordenar por columna Prioridad) para que los acumulados se recalculen bien.
A31: 3) El tier "CERRO" (locales que cierran / cambian de dueño y no renuevan) se excluye automaticamente de los 3 escenarios, sin consumir presupuesto (1 contrato: Helena Beach, ZBB, $110.000.000).
A32: 4) "Cliente" = cada fila / punto de venta (Nombre de Fantasia). Un mismo Razon Social/Distribuidor puede tener varios clientes (ej. COMERCIAL DEL MAR SA).
A33: 5) El universo completo (75 contratos sin CERRO) requiere aprox. $2.028M bajo Criterio 1, $2.188M bajo Criterio 3 (punto medio) y $2.706M bajo Criterio 2 para renovarse por completo. Los 3 escenarios ($1.430M / $1.650M / $2.000M) quedan por debajo en la mayoria de los casos: usar la hoja RESUMEN para ver cuanto alcanza cada uno.
A35: ALERTAS DE CALIDAD DE DATO (revisar antes de presentar)
A36: Helena Beach (ZBB, COMERCIAL DEL MAR SA) | C36: Codigo cliente = "CERRO CAMBIA DE DUEÑOS Y FORMATO" y tier=CERRO. El "FEE ACTUALIZADO" (Criterio 1) vino en $0 (sin dato de origen). Excluido de todos los escenarios por ser CERRO.
A37: Casa Pampa (ZBB, COMERCIAL DEL MAR SA) | C37: Codigo cliente = "CERRO CAMBIA DE FORMATO PARA SER CALAMAR LOCO HOSTELS" pero tier de ventas = IMPERDIBLE (cambia de formato/marca pero continuaria). Confirmar si corresponde mantenerlo como renovable.
A38: Negroni Helena (ZBB, BEBIDAS DEL MAR S.A.) | C38: Codigo cliente = "CERRO" y el comentario dice "No renueva; cerro", pero el tier quedo IMPERDIBLE. Contradiccion a resolver: hoy se mantiene como IMPERDIBLE en el ranking.
A39: El Descorche (ZBB, BEER TAN S.A.) | C39: Comentario: "Renueva sin fee; no tiene volumen significativo y no esta en LOL". Podria no requerir presupuesto para renovarse (fee=0). Se mantuvo con su Monto FEE actual por consistencia.
A40: El Calamar Loco PG (TS, COMERCIAL DEL MAR SA) | C40: El "FEE ACTUALIZADO" (Criterio 1) vino en $0 en el archivo original (sin dato de origen / formula rota). Verificar valor real de mercado antes de usar Criterio 1 para este contrato.
A41: Honu Beach (TS, COMERCIAL DEL MAR SA) | C41: El "FEE ACTUALIZADO" (Criterio 1) vino en $0 en el archivo original (sin dato de origen / formula rota). Verificar valor real de mercado antes de usar Criterio 1 para este contrato.

Sheet BASE
A1: Prioridad | B1: Tier Base | C1: Bolsa | D1: Comentario | E1: Codigo Cliente | F1: Cliente / PDV (Nombre de Fantasia) | G1: Razon Social (Distribuidor) | H1: Marca | I1: Rubro | J1: Vigencia Desde | K1: Vigencia Hasta | L1: Duracion (meses) | M1: Comentario original | N1: Monto FEE Actual (pagado) | O1: % Inflacion acumulada aplicable | P1: Criterio 1 - PAUTA CMQ | Q1: Criterio 2 - FEE + Inflacion | R1: Criterio 3 - Punto medio | S1: Acumulado Criterio 1: PAUTA CMQ | T1: Acumulado Criterio 2: INFLACION | U1: Acumulado Criterio 3: PUNTO MEDIO | V1: ESCENARIO 1: ZBB 1.400M | W1: ESCENARIO 2: ZBB + TS 50% 1.600M | X1: ESCENARIO 3 ZBB+ TS: 2.000M
A2: 1 | B2: IMPERDIBLE | C2: TS | E2: 20121 | F2: El Calamar Loco Chapa | G2: LA NIDADA CHAPADMALAL S. A. | H2: Corona | I2: NOCTURNIDAD/EVENTOS | J2: 46023 | K2: 46388 | L2: 12 | M2: Vence post 2026; charlar mas adelante | N2: 200000000 | O2: 0.25 | P2: 1.9197339e+08 | Q2: =N2*(1+O2) | R2: =AVERAGE(P2,Q2) | S2: =IF(B2="CERRO",0,P2) | T2: =IF(B2="CERRO",0,Q2) | U2: =IF(B2="CERRO",0,R2) | V2: SI | W2: SI | X2: SI
A3: 2 | B3: IMPERDIBLE | C3: ZBB | E3: 60743 | F3: Mr Jones | G3: Playa Bacana SA | H3: Budweiser | I3: NOCTURNIDAD/EVENTOS | J3: 45658 | K3: 46388 | L3: 24 | M3: Vence post 2026; charlar mas adelante | N3: 170000000 | O3: 0.68 | P3: 1.9319517e+08 | Q3: =N3*(1+O3) | R3: =AVERAGE(P3,Q3) | S3: =IF(B3="CERRO",S2,S2+P3) | T3: =IF(B3="CERRO",T2,T2+Q3) | U3: =IF(B3="CERRO",U2,U2+R3) | V3: SI | W3: SI | X3: SI
A4: 3 | B4: IMPERDIBLE | C4: ZBB | E4: 60635 | F4: Quba | G4: Purasal SRL | H4: Budweiser | I4: NOCTURNIDAD/EVENTOS | J4: 45658 | K4: 46388 | L4: 24 | M4: Vence post 2026; charlar mas adelante | N4: 160000000 | O4: 0.68 | P4: 1.8183075e+08 | Q4: =N4*(1+O4) | R4: =AVERAGE(P4,Q4) | S4: =IF(B4="CERRO",S3,S3+P4) | T4: =IF(B4="CERRO",T3,T3+Q4) | U4: =IF(B4="CERRO",U3,U3+R4) | V4: SI | W4: SI | X4: SI
A5: 4 | B5: IMPERDIBLE | C5: ZBB | E5: 1358 | F5: Tante-Masse-La cabrera | G5: Premium s.a | H5: Stella Artois | I5: GASTRONOMIA | J5: 45658 | K5: 46388 | L5: 24 | M5: Vence post 2026; charlar mas adelante | N5: 140000000 | O5: 0.68 | P5: 1.5910191e+08 | Q5: =N5*(1+O5) | R5: =AVERAGE(P5,Q5) | S5: =IF(B5="CERRO",S4,S4+P5) | T5: =IF(B5="CERRO",T4,T4+Q5) | U5: =IF(B5="CERRO",U4,U4+R5) | V5: SI | W5: SI | X5: SI
A6: 5 | B6: IMPERDIBLE | C6: ZBB | E6: 60834 | F6: Bruto | G6: Distribución Monkey SA | H6: Budweiser | I6: NOCTURNIDAD/EVENTOS | J6: 45292 | K6: 46388 | L6: 36 | M6: Vence post 2026; charlar mas adelante | N6: 95000000 | O6: 2.13 | P6: 3.133714e+08 | Q6: =N6*(1+O6) | R6: =AVERAGE(P6,Q6) | S6: =IF(B6="CERRO",S5,S5+P6) | T6: =IF(B6="CERRO",T5,T5+Q6) | U6: =IF(B6="CERRO",U5,U5+R6) | V6: SI | W6: SI | X6: SI
A7: 6 | B7: IMPERDIBLE | C7: ZBB | E7: 62866 | F7: Samsara | G7: Sunny Beach SA | H7: Brahma | I7: NOCTURNIDAD/EVENTOS | J7: 45658 | K7: 46388 | L7: 24 | M7: Vence post 2026; charlar mas adelante | N7: 75000000 | O7: 0.68 | P7: 85233164 | Q7: =N7*(1+O7) | R7: =AVERAGE(P7,Q7) | S7: =IF(B7="CERRO",S6,S6+P7) | T7: =IF(B7="CERRO",T6,T6+Q7) | U7: =IF(B7="CERRO",U6,U6+R7) | V7: SI | W7: SI | X7: SI
A8: 7 | B8: IMPERDIBLE | C8: ZBB | E8: 0 | F8: La Gamba | G8: Eras comercializaciones S.R.L | H8: Stella Artois | I8: BALNEARIOS | J8: 45658 | K8: 46388 | L8: 24 | M8: Vence post 2026; charlar mas adelante | N8: 60000000 | O8: 0.68 | P8: 68186531 | Q8: =N8*(1+O8) | R8: =AVERAGE(P8,Q8) | S8: =IF(B8="CERRO",S7,S7+P8) | T8: =IF(B8="CERRO",T7,T7+Q8) | U8: =IF(B8="CERRO",U7,U7+R8) | V8: SI | W8: SI | X8: SI
A9: 8 | B9: IMPERDIBLE | C9: TS | E9: 25769 | F9: Luna Roja | G9: E.J.C. S.A. | H9: Corona | I9: BALNEARIOS | J9: 46023 | K9: 46388 | L9: 12 | M9: Vence post 2026; charlar mas adelante | N9: 60000000 | O9: 0.25 | P9: 57592018 | Q9: =N9*(1+O9) | R9: =AVERAGE(P9,Q9) | S9: =IF(B9="CERRO",S8,S8+P9) | T9: =IF(B9="CERRO",T8,T8+Q9) | U9: =IF(B9="CERRO",U8,U8+R9) | V9: SI | W9: SI | X9: SI
A10: 9 | B10: IMPERDIBLE | C10: TS | D10: no habia pauta cmq | E10: 63412 | F10: El Calamar Loco PG | G10: BRUNNI BEACH 33 S.A. | H10: Corona | I10: NOCTURNIDAD/EVENTOS | J10: 46023 | K10: 46388 | L10: 12 | M10: Vence post 2026; charlar mas adelante | N10: 41000000 | O10: 0.25 | P10: 41000000 | Q10: =N10*(1+O10) | R10: =AVERAGE(P10,Q10) | S10: =IF(B10="CERRO",S9,S9+P10) | T10: =IF(B10="CERRO",T9,T9+Q10) | U10: =IF(B10="CERRO",U9,U9+R10) | V10: NO | W10: SI | X10: SI
A11: 10 | B11: IMPERDIBLE | C11: TS | E11: 64509 | F11: Bendu | G11: Monograma SRL | H11: Quilmes | I11: NOCTURNIDAD/EVENTOS | J11: 46023 | K11: 46388 | L11: 12 | M11: Vence post 2026; charlar mas adelante | N11: 40000000 | O11: 0.25 | P11: 38394679 | Q11: =N11*(1+O11) | R11: =AVERAGE(P11,Q11) | S11: =IF(B11="CERRO",S10,S10+P11) | T11: =IF(B11="CERRO",T10,T10+Q11) | U11: =IF(B11="CERRO",U10,U10+R11) | V11: NO | W11: SI | X11: SI
A12: 11 | B12: IMPERDIBLE | C12: TS | E12: 2247 | F12: Pueblo Límite | G12: Pueblo Límite SAS | H12: Brahma | I12: NOCTURNIDAD/EVENTOS | J12: 46023 | K12: 46388 | L12: 12 | M12: Vence post 2026; charlar mas adelante | N12: 30000000 | O12: 0.25 | P12: 28796009 | Q12: =N12*(1+O12) | R12: =AVERAGE(P12,Q12) | S12: =IF(B12="CERRO",S11,S11+P12) | T12: =IF(B12="CERRO",T11,T11+Q12) | U12: =IF(B12="CERRO",U11,U11+R12) | V12: NO | W12: SI | X12: SI
A13: 12 | B13: IMPERDIBLE | C13: ZBB | D13: fee reservado para casa calamar | E13: CERRO CAMBIA DE FORMATO PARA SER CALAMAR LOCO HOSTELS | F13: Casa Pampa | G13: SANTIAGO DE COMPOSTELA 1943 S.A. | H13: Stella Artois | I13: GASTRONOMIA | J13: 45658 | K13: 46388 | L13: 24 | M13: Vence post 2026; charlar mas adelante | N13: 25000000 | O13: 0.68 | P13: 28411055 | Q13: =N13*(1+O13) | R13: =AVERAGE(P13,Q13) | S13: =IF(B13="CERRO",S12,S12+P13) | T13: =IF(B13="CERRO",T12,T12+Q13) | U13: =IF(B13="CERRO",U12,U12+R13) | V13: NO | W13: SI | X13: SI
A14: 13 | B14: IMPERDIBLE | C14: ZBB | E14: 60973 | F14: ESTACION CENTRAL | G14: VAMOELPACK MDP S.A. | H14: Corona | I14: NOCTURNIDAD/EVENTOS | J14: 45292 | K14: 46388 | L14: 36 | M14: Vence post 2026; charlar mas adelante | N14: 25000000 | O14: 2.13 | P14: 56076988 | Q14: =N14*(1+O14) | R14: =AVERAGE(P14,Q14) | S14: =IF(B14="CERRO",S13,S13+P14) | T14: =IF(B14="CERRO",T13,T13+Q14) | U14: =IF(B14="CERRO",U13,U13+R14) | V14: NO | W14: NO | X14: SI
A15: 14 | B15: IMPERDIBLE | C15: TS | E15: 6728 | F15: Casa Mar | G15: JR COMUNICACIONES SRL | H15: Stella Artois | I15: BALNEARIOS | J15: 46023 | K15: 46388 | L15: 12 | M15: Vence post 2026; charlar mas adelante | N15: 17500000 | O15: 0.25 | P15: 16797672 | Q15: =N15*(1+O15) | R15: =AVERAGE(P15,Q15) | S15: =IF(B15="CERRO",S14,S14+P15) | T15: =IF(B15="CERRO",T14,T14+Q15) | U15: =IF(B15="CERRO",U14,U14+R15) | V15: NO | W15: NO | X15: SI
A16: 15 | B16: IMPERDIBLE | C16: ZBB | E16: 60917 | F16: LOS TOLDOS VIEJOS | G16: COUNTRY GRILLS S. R. L. | H16: Stella Artois | I16: GASTRONOMIA | J16: 45658 | K16: 46388 | L16: 24 | M16: Vence post 2026; charlar mas adelante | N16: 16000000 | O16: 0.68 | P16: 18183075 | Q16: =N16*(1+O16) | R16: =AVERAGE(P16,Q16) | S16: =IF(B16="CERRO",S15,S15+P16) | T16: =IF(B16="CERRO",T15,T15+Q16) | U16: =IF(B16="CERRO",U15,U15+R16) | V16: NO | W16: NO | X16: SI
A17: 16 | B17: IMPERDIBLE | C17: ZBB | E17: 62431 | F17: Villa Aluminé | G17: Villa Aluminé SA | H17: Stella Artois | I17: NOCTURNIDAD/EVENTOS | J17: 45658 | K17: 46388 | L17: 24 | M17: Vence post 2026; charlar mas adelante | N17: 16000000 | O17: 0.68 | P17: 18183075 | Q17: =N17*(1+O17) | R17: =AVERAGE(P17,Q17) | S17: =IF(B17="CERRO",S16,S16+P17) | T17: =IF(B17="CERRO",T16,T16+Q17) | U17: =IF(B17="CERRO",U16,U16+R17) | V17: NO | W17: NO | X17: SI
A18: 17 | B18: IMPERDIBLE | C18: TS | E18: 9558 | F18: EDV | G18: Racing Experience S.A | H18: Corona | I18: BALNEARIOS | J18: 46023 | K18: 46388 | L18: 12 | M18: Vence post 2026; charlar mas adelante | N18: 11000000 | O18: 0.25 | P18: 10558537 | Q18: =N18*(1+O18) | R18: =AVERAGE(P18,Q18) | S18: =IF(B18="CERRO",S17,S17+P18) | T18: =IF(B18="CERRO",T17,T17+Q18) | U18: =IF(B18="CERRO",U17,U17+R18) | V18: NO | W18: NO | X18: SI
A19: 18 | B19: IMPERDIBLE | C19: TS | E19: 61950 | F19: Bosques del Faro | G19: Bosques del Faro SRL | H19: Corona | I19: BALNEARIOS | J19: 46023 | K19: 46388 | L19: 12 | M19: Vence post 2026; charlar mas adelante | N19: 10000000 | O19: 0.25 | P19: 9598669.7 | Q19: =N19*(1+O19) | R19: =AVERAGE(P19,Q19) | S19: =IF(B19="CERRO",S18,S18+P19) | T19: =IF(B19="CERRO",T18,T18+Q19) | U19: =IF(B19="CERRO",U18,U18+R19) | V19: NO | W19: NO | X19: SI
A20: 19 | B20: IMPERDIBLE | C20: ZBB | E20: 60962 | F20: Cava Federal | G20: Jiro MDQ SA | H20: Stella Artois | I20: NOCTURNIDAD/EVENTOS | J20: 45597 | K20: 46327 | L20: 24 | M20: Renueva; | N20: 10000000 | O20: 0.68 | P20: 11754067 | Q20: =N20*(1+O20) | R20: =AVERAGE(P20,Q20) | S20: =IF(B20="CERRO",S19,S19+P20) | T20: =IF(B20="CERRO",T19,T19+Q20) | U20: =IF(B20="CERRO",U19,U19+R20) | V20: NO | W20: NO | X20: SI
A21: 20 | B21: IMPERDIBLE | C21: ZBB | E21: 8242 | F21: Palma Bristo Amarras | G21: Morosenlacosta | H21: Corona | I21: BALNEARIOS | J21: 45292 | K21: 46388 | L21: 36 | M21: Vence post 2026; charlar mas adelante | N21: 10000000 | O21: 2.13 | P21: 22430795 | Q21: =N21*(1+O21) | R21: =AVERAGE(P21,Q21) | S21: =IF(B21="CERRO",S20,S20+P21) | T21: =IF(B21="CERRO",T20,T20+Q21) | U21: =IF(B21="CERRO",U20,U20+R21) | V21: NO | W21: NO | X21: SI
A22: 21 | B22: IMPERDIBLE | C22: TS | E22: 60330 | F22: Waikiki | G22: PERGAMINO DEL MAR S.R.L. | H22: Stella Artois | I22: GASTRONOMIA | J22: 46023 | K22: 46388 | L22: 12 | M22: Vence post 2026; charlar mas adelante | N22: 10000000 | O22: 0.25 | P22: 9598669.7 | Q22: =N22*(1+O22) | R22: =AVERAGE(P22,Q22) | S22: =IF(B22="CERRO",S21,S21+P22) | T22: =IF(B22="CERRO",T21,T21+Q22) | U22: =IF(B22="CERRO",U21,U21+R22) | V22: NO | W22: NO | X22: SI
A23: 22 | B23: IMPERDIBLE | C23: TS | E23: 4124 | F23: Hemingway | G23: HMNGWY S,A | H23: Corona | I23: BALNEARIOS | J23: 46023 | K23: 46388 | L23: 12 | M23: Vence post 2026; charlar mas adelante | N23: 8000000 | O23: 0.25 | P23: 7678935.7 | Q23: =N23*(1+O23) | R23: =AVERAGE(P23,Q23) | S23: =IF(B23="CERRO",S22,S22+P23) | T23: =IF(B23="CERRO",T22,T22+Q23) | U23: =IF(B23="CERRO",U22,U22+R23) | V23: NO | W23: NO | X23: SI
A24: 23 | B24: IMPERDIBLE | C24: ZBB | E24: 4967 | F24: Mattone | G24: Bunge y Mar SA | H24: Stella Artois | I24: GASTRONOMIA | J24: 45658 | K24: 46388 | L24: 24 | M24: Vence post 2026; charlar mas adelante | N24: 6000000 | O24: 0.68 | P24: 6818653.1 | Q24: =N24*(1+O24) | R24: =AVERAGE(P24,Q24) | S24: =IF(B24="CERRO",S23,S23+P24) | T24: =IF(B24="CERRO",T23,T23+Q24) | U24: =IF(B24="CERRO",U23,U23+R24) | V24: NO | W24: NO | X24: SI
A25: 24 | B25: IMPERDIBLE | C25: TS | E25: 1368 | F25: CR | G25: Fernandez y Fernandez S.H. | H25: Corona | I25: BALNEARIOS | J25: 46023 | K25: 46388 | L25: 12 | M25: Vence post 2026; charlar mas adelante | N25: 5000000 | O25: 0.25 | P25: 4799334.8 | Q25: =N25*(1+O25) | R25: =AVERAGE(P25,Q25) | S25: =IF(B25="CERRO",S24,S24+P25) | T25: =IF(B25="CERRO",T24,T24+Q25) | U25: =IF(B25="CERRO",U24,U24+R25) | V25: NO | W25: NO | X25: SI
... A29: 28 | B29: IMPERDIBLE | C29: ZBB | E29: 8545 | F29: Hondo | G29: De Jesús Juan Aramis | H29: Stella Artois | I29: GASTRONOMIA | J29: 45627 | K29: 46357 | L29: 24 | M29: Pendiente de revisar con región | N29: 4000000 | O29: 0.68 | P29: 4596292.2 | Q29: =N29*(1+O29) | R29: =AVERAGE(P29,Q29) | S29: =IF(B29="CERRO",S28,S28+P29) | T29: =IF(B29="CERRO",T28,T28+Q29) | U29: =IF(B29="CERRO",U28,U28+R29) | V29: NO | W29: NO | X29: SI
A30: 29 | B30: IMPERDIBLE | C30: ZBB | F30: Negroni pinamar | G30: LOJAPAZ PINAMAR S.A. | H30: Stella Artois | I30: BALNEARIOS | J30: 45597 | K30: 46327 | L30: 24 | M30: No renueva; cerro | N30: 4000000 | O30: 0.68 | P30: 4701626.7 | Q30: =N30*(1+O30) | R30: =AVERAGE(P30,Q30) | S30: =IF(B30="CERRO",S29,S29+P30) | T30: =IF(B30="CERRO",T29,T29+Q30) | U30: =IF(B30="CERRO",U29,U29+R30) | V30: NO | W30: NO | X30: SI
A31: 30 | B31: IMPERDIBLE | C31: ZBB | E31: 5978 | F31: Cooperativa de Pesca | G31: Cooperativa de trabajo artesanal pescadores de Pinamar ltda | H31: Quilmes | I31: GASTRONOMIA | J31: 45658 | K31: 46388 | L31: 24 | M31: Vence post 2026; charlar mas adelante | N31: 3500000 | O31: 0.68 | P31: 4679467.8 | Q31: =N31*(1+O31) | R31: =AVERAGE(P31,Q31) | S31: =IF(B31="CERRO",S30,S30+P31) | T31: =IF(B31="CERRO",T30,T30+Q31) | U31: =IF(B31="CERRO",U30,U30+R31) | V31: NO | W31: NO | X31: SI
A32: 31 | B32: IMPERDIBLE | C32: TS | E32: 8194 | F32: Kai Bar | G32: Kai Esmeralda SA | H32: Corona | I32: GASTRONOMIA | J32: 46023 | K32: 46388 | L32: 12 | M32: Vence post 2026; charlar mas adelante | N32: 2200000 | O32: 0.25 | P32: 2111707.3 | Q32: =N32*(1+O32) | R32: =AVERAGE(P32,Q32) | S32: =IF(B32="CERRO",S31,S31+P32) | T32: =IF(B32="CERRO",T31,T31+Q32) | U32: =IF(B32="CERRO",U31,U31+R32) | V32: NO | W32: NO | X32: SI
A33: 32 | B33: IMPERDIBLE | C33: TS | E33: 9313 | F33: Parentela | G33: Fuera del Molde SA | H33: Stella Artois | I33: GASTRONOMIA | J33: 46023 | K33: 46388 | L33: 12 | M33: Vence post 2026; charlar mas adelante | N33: 1200000 | O33: 0.25 | P33: 1060263.1 | Q33: =N33*(1+O33) | R33: =AVERAGE(P33,Q33) | S33: =IF(B33="CERRO",S32,S32+P33) | T33: =IF(B33="CERRO",T32,T32+Q33) | U33: =IF(B33="CERRO",U32,U32+R33) | V33: NO | W33: NO | X33: SI
A34: 33 | B34: DISCUTIBLE | C34: TS | E34: 60620 | F34: La Normandina | G34: Paseo Normandie SA | H34: Brahma | I34: NOCTURNIDAD/EVENTOS | J34: 46023 | K34: 46388 | L34: 12 | M34: Vence post 2026; charlar mas adelante | N34: 70000000 | O34: 0.25 | P34: 67190688 | Q34: =N34*(1+O34) | R34: =AVERAGE(P34,Q34) | S34: =IF(B34="CERRO",S33,S33+P34) | T34: =IF(B34="CERRO",T33,T33+Q34) | U34: =IF(B34="CERRO",U33,U33+R34) | V34: NO | W34: NO | X34: SI
A35: 34 | B35: DISCUTIBLE | C35: ZBB | E35: 3238 | F35: Brothers | G35: Diego Heter | H35: Patagonia | I35: NOCTURNIDAD/EVENTOS | J35: 45627 | K35: 46357 | L35: 24 | M35: Pendiente de revisar con región | N35: 65000000 | O35: 0.68 | P35: 74689748 | Q35: =N35*(1+O35) | R35: =AVERAGE(P35,Q35) | S35: =IF(B35="CERRO",S34,S34+P35) | T35: =IF(B35="CERRO",T34,T34+Q35) | U35: =IF(B35="CERRO",U34,U34+R35) | V35: NO | W35: NO | X35: NO
A36: 35 | B36: DISCUTIBLE | C36: ZBB | E36: 8383 | F36: Camping Americano | G36: EPICURAE AMERICANOSERV S.A | H36: Corona | I36: OTROS | J36: 45627 | K36: 46357 | L36: 24 | M36: Pendiente de revisar con región | N36: 11000000 | O36: 0.68 | P36: 12639804 | Q36: =N36*(1+O36) | R36: =AVERAGE(P36,Q36) | S36: =IF(B36="CERRO",S35,S35+P36) | T36: =IF(B36="CERRO",T35,T35+Q36) | U36: =IF(B36="CERRO",U35,U35+R36) | V36: NO | W36: NO | X36: NO
A37: 36 | B37: DISCUTIBLE | C37: ZBB | E37: 60931 | F37: Mambrú | G37: BALL LLATINAS FERNANDO JORGE | H37: Quilmes | I37: GASTRONOMIA | J37: 45658 | K37: 46388 | L37: 24 | M37: Vence post 2026; charlar mas adelante | N37: 8000000 | O37: 0.68 | P37: 9091537.5 | Q37: =N37*(1+O37) | R37: =AVERAGE(P37,Q37) | S37: =IF(B37="CERRO",S36,S36+P37) | T37: =IF(B37="CERRO",T36,T36+Q37) | U37: =IF(B37="CERRO",U36,U36+R37) | V37: NO | W37: NO | X37: NO
A38: 37 | B38: DISCUTIBLE | C38: TS | E38: 60692 | F38: El Condor | G38: ANJUFA S.A. | H38: Stella Artois | I38: GASTRONOMIA | J38: 46023 | K38: 46388 | L38: 12 | M38: Vence post 2026; charlar mas adelante | N38: 2200000 | O38: 0.25 | P38: 2111707.3 | Q38: =N38*(1+O38) | R38: =AVERAGE(P38,Q38) | S38: =IF(B38="CERRO",S37,S37+P38) | T38: =IF(B38="CERRO",T37,T37+Q38) | U38: =IF(B38="CERRO",U37,U37+R38) | V38: NO | W38: NO | X38: NO
A39: 38 | B39: DISCUTIBLE | C39: TS | E39: 9452 | F39: Olivo | G39: ARABIA GASTRONOMICA S.R.L. | H39: Stella Artois | I39: GASTRONOMIA | J39: 46023 | K39: 46388 | L39: 12 | M39: Vence post 2026; charlar mas adelante | N39: 1800000 | O39: 0.25 | P39: 1727760.5 | Q39: =N39*(1+O39) | R39: =AVERAGE(P39,Q39) | S39: =IF(B39="CERRO",S38,S38+P39) | T39: =IF(B39="CERRO",T38,T38+Q39) | U39: =IF(B39="CERRO",U38,U38+R39) | V39: NO | W39: NO | X39: NO
A40: 39 | B40: DISCUTIBLE | C40: ZBB | E40: 61033 | F40: NEREA | G40: SHAW AND BEACH S.A. | H40: Stella Artois | I40: GASTRONOMIA | J40: 45627 | K40: 46357 | L40: 24 | M40: Pendiente de revisar con región | N40: 1700000 | O40: 0.68 | P40: 1953424.2 | Q40: =N40*(1+O40) | R40: =AVERAGE(P40,Q40) | S40: =IF(B40="CERRO",S39,S39+P40) | T40: =IF(B40="CERRO",T39,T39+Q40) | U40: =IF(B40="CERRO",U39,U39+R40) | V40: NO | W40: NO | X40: NO
A41: 40 | B41: DISCUTIBLE | C41: TS | E41: 60233 | F41: El Taino | G41: Playas del Vesubio SRL | H41: Brahma | I41: BALNEARIOS | J41: 46023 | K41: 46388 | L41: 12 | M41: Vence post 2026; charlar mas adelante | N41: 1200000 | O41: 0.25 | P41: 1151840.4 | Q41: =N41*(1+O41) | R41: =AVERAGE(P41,Q41) | S41: =IF(B41="CERRO",S40,S40+P41) | T41: =IF(B41="CERRO",T40,T40+Q41) | U41: =IF(B41="CERRO",U40,U40+R41) | V41: NO | W41: NO | X41: NO
A42: 41 | B42: DISCUTIBLE | C42: ZBB | E42: 62691 | F42: Lo de Fran | G42: SALITRE MARINO S. A. | H42: Stella Artois | I42: GASTRONOMIA | J42: 45536 | K42: 46266 | L42: 24 | M42: Renueva; | N42: 21000000 | O42: 0.68 | P42: 25827863 | Q42: =N42*(1+O42) | R42: =AVERAGE(P42,Q42) | S42: =IF(B42="CERRO",S41,S41+P42) | T42: =IF(B42="CERRO",T41,T41+Q42) | U42: =IF(B42="CERRO",U41,U41+R42) | V42: NO | W42: NO | X42: NO
... A44: 43 | B44: DISCUTIBLE | C44: TS | E44: 63944 | F44: Espacio Pueyrredón | G44: AMOR ES LA RESPUESTA S.A. | H44: Quilmes | I44: GASTRONOMIA | J44: 46082 | K44: 46388 | L44: 10 | M44: Vence post 2026; charlar mas adelante | N44: 17000000 | O44: 0.25 | P44: 15786081 | Q44: =N44*(1+O44) | R44: =AVERAGE(P44,Q44) | S44: =IF(B44="CERRO",S43,S43+P44) | T44: =IF(B44="CERRO",T43,T43+Q44) | U44: =IF(B44="CERRO",U43,U43+R44) | V44: NO | W44: NO | X44: NO
A45: 44 | B45: DISCUTIBLE | C45: TS | D45: no habia pauta cmq | E45: 60357 | F45: Honu Beach | G45: SOL SUR HOBE S.A. | H45: Corona | I45: BALNEARIOS | J45: 46023 | K45: 46388 | L45: 12 | M45: Vence post 2026; charlar mas adelante | N45: 15000000 | O45: 0.25 | P45: 15000000 | Q45: =N45*(1+O45) | R45: =AVERAGE(P45,Q45) | S45: =IF(B45="CERRO",S44,S44+P45) | T45: =IF(B45="CERRO",T44,T44+Q45) | U45: =IF(B45="CERRO",U44,U44+R45) | V45: NO | W45: NO | X45: NO
A46: 45 | B46: DISCUTIBLE | C46: ZBB | E46: 0 | F46: mama Concert | G46: Pinamar S.A | H46: Corona | I46: BALNEARIOS | J46: 45658 | K46: 46388 | L46: 24 | M46: Vence post 2026; charlar mas adelante | N46: 15000000 | O46: 0.68 | P46: 68186531 | Q46: =N46*(1+O46) | R46: =AVERAGE(P46,Q46) | S46: =IF(B46="CERRO",S45,S45+P46) | T46: =IF(B46="CERRO",T45,T45+Q46) | U46: =IF(B46="CERRO",U45,U45+R46) | V46: NO | W46: NO | X46: NO
A47: 46 | B47: DISCUTIBLE | C47: ZBB | E47: 4822 | F47: Mirador Tandil | G47: GASTRO LLE TANDIL S.A.S | H47: Patagonia | I47: GASTRONOMIA | J47: 45658 | K47: 46388 | L47: 24 | M47: Vence post 2026; charlar mas adelante | N47: 15000000 | O47: 0.68 | P47: 17046633 | Q47: =N47*(1+O47) | R47: =AVERAGE(P47,Q47) | S47: =IF(B47="CERRO",S46,S46+P47) | T47: =IF(B47="CERRO",T46,T46+Q47) | U47: =IF(B47="CERRO",U46,U46+R47) | V47: NO | W47: NO | X47: NO
A48: 47 | B48: DISCUTIBLE | C48: TS | E48: 63459 | F48: Newbery | G48: ASOCIACION CIVIL NBRY ATHLETIC FC, C | H48: Stella Artois | I48: OTROS | J48: 46023 | K48: 46388 | L48: 12 | M48: Vence post 2026; charlar mas adelante | N48: 14000000 | O48: 0.25 | P48: 13438138 | Q48: =N48*(1+O48) | R48: =AVERAGE(P48,Q48) | S48: =IF(B48="CERRO",S47,S47+P48) | T48: =IF(B48="CERRO",T47,T47+Q48) | U48: =IF(B48="CERRO",U47,U47+R48) | V48: NO | W48: NO | X48: NO
A49: 48 | B49: DISCUTIBLE | C49: TS | E49: 7631 | F49: Barra Beach | G49: Eras Comercializaciones S.R.L | H49: Corona | I49: BALNEARIOS | J49: 46023 | K49: 46388 | L49: 12 | M49: Vence post 2026; charlar mas adelante | N49: 12000000 | O49: 0.25 | P49: 11518404 | Q49: =N49*(1+O49) | R49: =AVERAGE(P49,Q49) | S49: =IF(B49="CERRO",S48,S48+P49) | T49: =IF(B49="CERRO",T48,T48+Q49) | U49: =IF(B49="CERRO",U48,U48+R49) | V49: NO | W49: NO | X49: NO
A50: 49 | B50: DISCUTIBLE | C50: TS | E50: 5836 | F50: Break 197 | G50: Consultora Nic S.A | H50: 0 | I50: GASTRONOMIA | J50: 46023 | K50: 46388 | L50: 12 | M50: Vence post 2026; charlar mas adelante | N50: 11500000 | O50: 0.25 | P50: 11038470 | Q50: =N50*(1+O50) | R50: =AVERAGE(P50,Q50) | S50: =IF(B50="CERRO",S49,S49+P50) | T50: =IF(B50="CERRO",T49,T49+Q50) | U50: =IF(B50="CERRO",U49,U49+R50) | V50: NO | W50: NO | X50: NO
A51: 50 | B51: DISCUTIBLE | C51: TS | E51: 61524 | F51: La Reserva | G51: Ocean Blue Strategy SA | H51: Stella Artois | I51: BALNEARIOS | J51: 46023 | K51: 46388 | L51: 12 | M51: Vence post 2026; charlar mas adelante | N51: 10000000 | O51: 0.25 | P51: 9598669.7 | Q51: =N51*(1+O51) | R51: =AVERAGE(P51,Q51) | S51: =IF(B51="CERRO",S50,S50+P51) | T51: =IF(B51="CERRO",T50,T50+Q51) | U51: =IF(B51="CERRO",U50,U50+R51) | V51: NO | W51: NO | X51: NO
A52: 51 | B52: DISCUTIBLE | C52: ZBB | E52: 60832 | F52: Pontevedra/Di Mero/Membrillo/Brasa | G52: PONTEBRAP S. A. | H52: Stella Artois | I52: GASTRONOMIA | J52: 45658 | K52: 46388 | L52: 24 | M52: Vence post 2026; charlar mas adelante | N52: 10000000 | O52: 0.68 | P52: 11364422 | Q52: =N52*(1+O52) | R52: =AVERAGE(P52,Q52) | S52: =IF(B52="CERRO",S51,S51+P52) | T52: =IF(B52="CERRO",T51,T51+Q52) | U52: =IF(B52="CERRO",U51,U51+R52) | V52: NO | W52: NO | X52: NO
A53: 52 | B53: DISCUTIBLE | C53: TS | E53: 60553 | F53: Tiki Bar | G53: Merlo Matias Leandro | H53: Corona | I53: GASTRONOMIA | J53: 46023 | K53: 46388 | L53: 12 | M53: Vence post 2026; charlar mas adelante | N53: 8000000 | O53: 0.25 | P53: 7678935.7 | Q53: =N53*(1+O53) | R53: =AVERAGE(P53,Q53) | S53: =IF(B53="CERRO",S52,S52+P53) | T53: =IF(B53="CERRO",T52,T52+Q53) | U53: =IF(B53="CERRO",U52,U52+R53) | V53: NO | W53: NO | X53: NO
A54: 53 | B54: DISCUTIBLE | C54: TS | E54: 2630 | F54: El Soleado | G54: Soleado de Cortazar M y Repetto M .S.A | H54: Stella Artois | I54: GASTRONOMIA | J54: 46023 | K54: 46388 | L54: 12 | M54: Vence post 2026; charlar mas adelante | N54: 7800000 | O54: 0.25 | P54: 7486962.3 | Q54: =N54*(1+O54) | R54: =AVERAGE(P54,Q54) | S54: =IF(B54="CERRO",S53,S53+P54) | T54: =IF(B54="CERRO",T53,T53+Q54) | U54: =IF(B54="CERRO",U53,U53+R54) | V54: NO | W54: NO | X54: NO
A55: 54 | B55: DISCUTIBLE | C55: TS | E55: 61058 | F55: Parque Mogotes | G55: PUNTO TOKEN MDK S. A. | H55: Quilmes | I55: NOCTURNIDAD/EVENTOS | J55: 46082 | K55: 46388 | L55: 10 | M55: Vence post 2026; charlar mas adelante | N55: 7000000 | O55: 0.25 | P55: 6500150.9 | Q55: =N55*(1+O55) | R55: =AVERAGE(P55,Q55) | S55: =IF(B55="CERRO",S54,S54+P55) | T55: =IF(B55="CERRO",T54,T54+Q55) | U55: =IF(B55="CERRO",U54,U54+R55) | V55: NO | W55: NO | X55: NO
A56: 55 | B56: DISCUTIBLE | C56: ZBB | E56: 62917 | F56: Hamburguesería Weiss | G56: Senno Gabriel | H56: Corona | I56: GASTRONOMIA | J56: 45717 | K56: 46357 | L56: 21 | M56: Pendiente de revisar con región | N56: 6000000 | O56: 0.68 | P56: 6346284.6 | Q56: =N56*(1+O56) | R56: =AVERAGE(P56,Q56) | S56: =IF(B56="CERRO",S55,S55+P56) | T56: =IF(B56="CERRO",T55,T55+Q56) | U56: =IF(B56="CERRO",U55,U55+R56) | V56: NO | W56: NO | X56: NO
A57: 56 | B57: DISCUTIBLE | C57: ZBB | E57: 5726 | F57: El Descorche | G57: Titno Rosado y Blanco SA | H57: Patagonia | I57: GASTRONOMIA | J57: 45566 | K57: 46296 | L57: 24 | M57: Renueva sin fee; no tiene volumen significativo y no esta en LOL | N57: 5800000 | O57: 0.68 | P57: 6973594.1 | Q57: =N57*(1+O57) | R57: =AVERAGE(P57,Q57) | S57: =IF(B57="CERRO",S56,S56+P57) | T57: =IF(B57="CERRO",T56,T56+Q57) | U57: =IF(B57="CERRO",U56,U56+R57) | V57: NO | W57: NO | X57: NO
A58: 57 | B58: DISCUTIBLE | C58: TS | E58: 60156 | F58: Baln 5,6,7 y 8 ACA | G58: AUTOMOVIL CLUB ARGENTINO | H58: Quilmes | I58: BALNEARIOS | J58: 45992 | K58: 46357 | L58: 12 | M58: No aplica es por TS | N58: 5200000 | O58: 0.25 | P58: 5046783.6 | Q58: =N58*(1+O58) | R58: =AVERAGE(P58,Q58) | S58: =IF(B58="CERRO",S57,S57+P58) | T58: =IF(B58="CERRO",T57,T57+Q58) | U58: =IF(B58="CERRO",U57,U57+R58) | V58: NO | W58: NO | X58: NO
A59: 58 | B59: DISCUTIBLE | C59: TS | E59: 9237 | F59: Casa Oxalis | G59: Lo Coco Fernando | H59: Stella Artois | I59: GASTRONOMIA | J59: 46023 | K59: 46388 | L59: 12 | M59: Vence post 2026; charlar mas adelante | N59: 4500000 | O59: 0.25 | P59: 4319401.4 | Q59: =N59*(1+O59) | R59: =AVERAGE(P59,Q59) | S59: =IF(B59="CERRO",S58,S58+P59) | T59: =IF(B59="CERRO",T58,T58+Q59) | U59: =IF(B59="CERRO",U58,U58+R59) | V59: NO | W59: NO | X59: NO
A60: 59 | B60: DISCUTIBLE | C60: TS | E60: 3961 | F60: Celina | G60: Establecimiento Ravasale S.R.L | H60: Corona | I60: BALNEARIOS | J60: 46023 | K60: 46388 | L60: 12 | M60: Vence post 2026; charlar mas adelante | N60: 4500000 | O60: 0.25 | P60: 4319401.4 | Q60: =N60*(1+O60) | R60: =AVERAGE(P60,Q60) | S60: =IF(B60="CERRO",S59,S59+P60) | T60: =IF(B60="CERRO",T59,T59+Q60) | U60: =IF(B60="CERRO",U59,U59+R60) | V60: NO | W60: NO | X60: NO
A61: 60 | B61: DISCUTIBLE | C61: ZBB | E61: 61357 | F61: Alamacén de carnes | G61: MARTIRE MARCOS EMANUEL | H61: Stella Artois | I61: GASTRONOMIA | J61: 45962 | K61: 46327 | L61: 12 | M61: Pendiente de revisar con región | N61: 3000000 | O61: 0.25 | P61: 2943966.6 | Q61: =N61*(1+O61) | R61: =AVERAGE(P61,Q61) | S61: =IF(B61="CERRO",S60,S60+P61) | T61: =IF(B61="CERRO",T60,T60+Q61) | U61: =IF(B61="CERRO",U60,U60+R61) | V61: NO | W61: NO | X61: NO
A62: 61 | B62: DISCUTIBLE | C62: TS | E62: 60927 | F62: Playas El Balcón | G62: Maktub SRL | H62: Stella Artois | I62: BALNEARIOS | J62: 46023 | K62: 46388 | L62: 12 | M62: Vence post 2026; charlar mas adelante | N62: 3000000 | O62: 0.25 | P62: 2879600.9 | Q62: =N62*(1+O62) | R62: =AVERAGE(P62,Q62) | S62: =IF(B62="CERRO",S61,S61+P62) | T62: =IF(B62="CERRO",T61,T61+Q62) | U62: =IF(B62="CERRO",U61,U61+R62) | V62: NO | W62: NO | X62: NO
... A76: 75 | B76: DISCUTIBLE | C76: TS | E76: 61577 | F76: Balneario 2 Alaciel | G76: Alazul SA | H76: Quilmes | I76: BALNEARIOS | J76: 45992 | K76: 46357 | L76: 12 | M76: No aplica es por TS | N76: 1300000 | O76: 0.25 | P76: 1261695.9 | Q76: =N76*(1+O76) | R76: =AVERAGE(P76,Q76) | S76: =IF(B76="CERRO",S75,S75+P76) | T76: =IF(B76="CERRO",T75,T75+Q76) | U76: =IF(B76="CERRO",U75,U75+R76) | V76: NO | W76: NO | X76: NO
M78: TOTAL 76 CONTRATOS (ZBB + TS) | N78: =SUM(N2:N76) | P78: =SUM(P2:P76) | Q78: =SUM(Q2:Q76) | R78: =SUM(R2:R76)

Sheet RESUMEN ESCENARIOS
A1: RESUMEN DE ESCENARIOS DE RENOVACION - FEE 2026 (76 contratos, ZBB + Trade Spend)
A2: Presupuesto de referencia: Criterio 3 - Punto medio (promedio entre Criterio 1 - FEE Actualizado y Criterio 2 - FEE + Inflacion). El contrato CERRO (Helena Beach, $110.000.000) no participa: cierra / cambia de dueno y no renueva.
A4: PRESUPUESTOS Y RESULTADO GLOBAL
A5: Escenario | B5: Descripcion | C5: Presupuesto | D5: Entran | E5: Pierden | F5: Monto usado (C3) | G5: Sobrante/Faltante | H5: Perdidos IMP | I5: Perdidos DISC
A6: Escenario 1 | B6: ZBB - presupuesto disponible hoy | C6: =PARAMETROS!$B$10 | D6: =COUNTIF(BASE!V2:V76,"SI") | E6: =COUNTIF(BASE!V2:V76,"NO") | F6: =SUMIFS(BASE!$R$2:$R$76,BASE!V2:V76,"SI") | G6: =C6-F6 | H6: =COUNTIFS(BASE!V2:V76,"NO",BASE!$B$2:$B$76,"IMPERDIBLE") | I6: =COUNTIFS(BASE!V2:V76,"NO",BASE!$B$2:$B$76,"DISCUTIBLE")
A7: Escenario 2 | B7: ZBB + adicional a conseguir | C7: =PARAMETROS!$B$13 | D7: =COUNTIF(BASE!W2:W76,"SI") | E7: =COUNTIF(BASE!W2:W76,"NO") | F7: =SUMIFS(BASE!$R$2:$R$76,BASE!W2:W76,"SI") | G7: =C7-F7 | H7: =COUNTIFS(BASE!W2:W76,"NO",BASE!$B$2:$B$76,"IMPERDIBLE") | I7: =COUNTIFS(BASE!W2:W76,"NO",BASE!$B$2:$B$76,"DISCUTIBLE")
A8: Escenario 3 | B8: ZBB + Trade Spend - presupuesto total | C8: =PARAMETROS!$B$14 | D8: =COUNTIF(BASE!X2:X76,"SI") | E8: =COUNTIF(BASE!X2:X76,"NO") | F8: =SUMIFS(BASE!$R$2:$R$76,BASE!X2:X76,"SI") | G8: =C8-F8 | H8: =COUNTIFS(BASE!X2:X76,"NO",BASE!$B$2:$B$76,"IMPERDIBLE") | I8: =COUNTIFS(BASE!X2:X76,"NO",BASE!$B$2:$B$76,"DISCUTIBLE")
A10: NOTA: "Luna Roja" figura "SI" en Escenario 1 aunque su acumulado (Criterio 3) supera el presupuesto en aprox. $14.340.900 (decision manual tomada en la hoja BASE). Se respeto tal cual esta.
A13: ESCENARIO 1 - CLIENTES QUE ENTRAN (ZBB - presupuesto disponible hoy)
A14: Prioridad | B14: Cliente / PDV | C14: Bolsa | D14: Tier | E14: Monto FEE Actual | F14: Criterio 3 - Punto medio
A15: 1 | B15: El Calamar Loco Chapa | C15: TS | D15: IMPERDIBLE | E15: 200000000 | F15: 2.209867e+08
A16: 2 | B16: Mr Jones | C16: ZBB | D16: IMPERDIBLE | E16: 170000000 | F16: 2.3939759e+08
A17: 3 | B17: Quba | C17: ZBB | D17: IMPERDIBLE | E17: 160000000 | F17: 2.2531538e+08
A18: 4 | B18: Tante-Masse-La cabrera | C18: ZBB | D18: IMPERDIBLE | E18: 140000000 | F18: 1.9715095e+08
A19: 5 | B19: Bruto | C19: ZBB | D19: IMPERDIBLE | E19: 95000000 | F19: 3.053607e+08
A20: 6 | B20: Samsara | C20: ZBB | D20: IMPERDIBLE | E20: 75000000 | F20: 1.0561658e+08
A21: 7 | B21: La Gamba | C21: ZBB | D21: IMPERDIBLE | E21: 60000000 | F21: 84493266
A22: 8 | B22: Luna Roja | C22: TS | D22: IMPERDIBLE | E22: 60000000 | F22: 66296009
B23: TOTAL 8 CLIENTES QUE ENTRAN | E23: =SUM(E15:E22) | F23: =SUM(F15:F22)
A25: ESCENARIO 1 - CLIENTES QUE SE PIERDEN (ZBB - presupuesto disponible hoy)
A26: Prioridad | B26: Cliente / PDV | C26: Bolsa | D26: Tier | E26: Monto FEE Actual | F26: Criterio 3 - Punto medio
A27: 9 | B27: El Calamar Loco PG | C27: TS | D27: IMPERDIBLE | E27: 41000000 | F27: 46125000
A28: 10 | B28: Bendu | C28: TS | D28: IMPERDIBLE | E28: 40000000 | F28: 44197339
A29: 11 | B29: Pueblo Límite | C29: TS | D29: IMPERDIBLE | E29: 30000000 | F29: 33148005
A30: 12 | B30: Casa Pampa | C30: ZBB | D30: IMPERDIBLE | E30: 25000000 | F30: 35205527
A31: 13 | B31: ESTACION CENTRAL | C31: ZBB | D31: IMPERDIBLE | E31: 25000000 | F31: 67163494
A32: 14 | B32: Casa Mar | C32: TS | D32: IMPERDIBLE | E32: 17500000 | F32: 19336336
A33: 15 | B33: LOS TOLDOS VIEJOS | C33: ZBB | D33: IMPERDIBLE | E33: 16000000 | F33: 22531538
A34: 16 | B34: Villa Aluminé | C34: ZBB | D34: IMPERDIBLE | E34: 16000000 | F34: 22531538
A35: 17 | B35: EDV | C35: TS | D35: IMPERDIBLE | E35: 11000000 | F35: 12154268
A36: 18 | B36: Bosques del Faro | C36: TS | D36: IMPERDIBLE | E36: 10000000 | F36: 11049335
A37: 19 | B37: Cava Federal | C37: ZBB | D37: IMPERDIBLE | E37: 10000000 | F37: 14277033
A38: 20 | B38: Palma Bristo Amarras | C38: ZBB | D38: IMPERDIBLE | E38: 10000000 | F38: 26865398
... A93: 75 | B93: Balneario 2 Alaciel | C93: TS | D93: DISCUTIBLE | E93: 1300000 | F93: 1443347.9
B94: TOTAL 67 CLIENTES QUE SE PIERDEN | E94: =SUM(E27:E93) | F94: =SUM(F27:F93)
A97: ESCENARIO 2 - CLIENTES QUE ENTRAN (ZBB + adicional a conseguir)
A98: Prioridad | B98: Cliente / PDV | C98: Bolsa | D98: Tier | E98: Monto FEE Actual | F98: Criterio 3 - Punto medio
A99: 1 | B99: El Calamar Loco Chapa | C99: TS | D99: IMPERDIBLE | E99: 200000000 | F99: 2.209867e+08
A100: 2 | B100: Mr Jones | C100: ZBB | D100: IMPERDIBLE | E100: 170000000 | F100: 2.3939759e+08
A101: 3 | B101: Quba | C101: ZBB | D101: IMPERDIBLE | E101: 160000000 | F101: 2.2531538e+08
A102: 4 | B102: Tante-Masse-La cabrera | C102: ZBB | D102: IMPERDIBLE | E102: 140000000 | F102: 1.9715095e+08
A103: 5 | B103: Bruto | C103: ZBB | D103: IMPERDIBLE | E103: 95000000 | F103: 3.053607e+08
A104: 6 | B104: Samsara | C104: ZBB | D104: IMPERDIBLE | E104: 75000000 | F104: 1.0561658e+08
A105: 7 | B105: La Gamba | C105: ZBB | D105: IMPERDIBLE | E105: 60000000 | F105: 84493266
A106: 8 | B106: Luna Roja | C106: TS | D106: IMPERDIBLE | E106: 60000000 | F106: 66296009
A107: 9 | B107: El Calamar Loco PG | C107: TS | D107: IMPERDIBLE | E107: 41000000 | F107: 46125000
A108: 10 | B108: Bendu | C108: TS | D108: IMPERDIBLE | E108: 40000000 | F108: 44197339
A109: 11 | B109: Pueblo Límite | C109: TS | D109: IMPERDIBLE | E109: 30000000 | F109: 33148005
A110: 12 | B110: Casa Pampa | C110: ZBB | D110: IMPERDIBLE | E110: 25000000 | F110: 35205527
B111: TOTAL 12 CLIENTES QUE ENTRAN | E111: =SUM(E99:E110) | F111: =SUM(F99:F110)
A113: ESCENARIO 2 - CLIENTES QUE SE PIERDEN (ZBB + adicional a conseguir)
A114: Prioridad | B114: Cliente / PDV | C114: Bolsa | D114: Tier | E114: Monto FEE Actual | F114: Criterio 3 - Punto medio
A115: 13 | B115: ESTACION CENTRAL | C115: ZBB | D115: IMPERDIBLE | E115: 25000000 | F115: 67163494
A116: 14 | B116: Casa Mar | C116: TS | D116: IMPERDIBLE | E116: 17500000 | F116: 19336336
A117: 15 | B117: LOS TOLDOS VIEJOS | C117: ZBB | D117: IMPERDIBLE | E117: 16000000 | F117: 22531538
A118: 16 | B118: Villa Aluminé | C118: ZBB | D118: IMPERDIBLE | E118: 16000000 | F118: 22531538
A119: 17 | B119: EDV | C119: TS | D119: IMPERDIBLE | E119: 11000000 | F119: 12154268
A120: 18 | B120: Bosques del Faro | C120: TS | D120: IMPERDIBLE | E120: 10000000 | F120: 11049335
A121: 19 | B121: Cava Federal | C121: ZBB | D121: IMPERDIBLE | E121: 10000000 | F121: 14277033
A122: 20 | B122: Palma Bristo Amarras | C122: ZBB | D122: IMPERDIBLE | E122: 10000000 | F122: 26865398
A123: 21 | B123: Waikiki | C123: TS | D123: IMPERDIBLE | E123: 10000000 | F123: 11049335
A124: 22 | B124: Hemingway | C124: TS | D124: IMPERDIBLE | E124: 8000000 | F124: 8839467.9
A125: 23 | B125: Mattone | C125: ZBB | D125: IMPERDIBLE | E125: 6000000 | F125: 8449326.6
A126: 24 | B126: CR | C126: TS | D126: IMPERDIBLE | E126: 5000000 | F126: 5524667.4
... A177: 75 | B177: Balneario 2 Alaciel | C177: TS | D177: DISCUTIBLE | E177: 1300000 | F177: 1443347.9
B178: TOTAL 63 CLIENTES QUE SE PIERDEN | E178: =SUM(E115:E177) | F178: =SUM(F115:F177)
A181: ESCENARIO 3 - CLIENTES QUE ENTRAN (ZBB + Trade Spend - presupuesto total)
A182: Prioridad | B182: Cliente / PDV | C182: Bolsa | D182: Tier | E182: Monto FEE Actual | F182: Criterio 3 - Punto medio
A183: 1 | B183: El Calamar Loco Chapa | C183: TS | D183: IMPERDIBLE | E183: 200000000 | F183: 2.209867e+08
A184: 2 | B184: Mr Jones | C184: ZBB | D184: IMPERDIBLE | E184: 170000000 | F184: 2.3939759e+08
A185: 3 | B185: Quba | C185: ZBB | D185: IMPERDIBLE | E185: 160000000 | F185: 2.2531538e+08
A186: 4 | B186: Tante-Masse-La cabrera | C186: ZBB | D186: IMPERDIBLE | E186: 140000000 | F186: 1.9715095e+08
A187: 5 | B187: Bruto | C187: ZBB | D187: IMPERDIBLE | E187: 95000000 | F187: 3.053607e+08
A188: 6 | B188: Samsara | C188: ZBB | D188: IMPERDIBLE | E188: 75000000 | F188: 1.0561658e+08
A189: 7 | B189: La Gamba | C189: ZBB | D189: IMPERDIBLE | E189: 60000000 | F189: 84493266
A190: 8 | B190: Luna Roja | C190: TS | D190: IMPERDIBLE | E190: 60000000 | F190: 66296009
A191: 9 | B191: El Calamar Loco PG | C191: TS | D191: IMPERDIBLE | E191: 41000000 | F191: 46125000
A192: 10 | B192: Bendu | C192: TS | D192: IMPERDIBLE | E192: 40000000 | F192: 44197339
A193: 11 | B193: Pueblo Límite | C193: TS | D193: IMPERDIBLE | E193: 30000000 | F193: 33148005
A194: 12 | B194: Casa Pampa | C194: ZBB | D194: IMPERDIBLE | E194: 25000000 | F194: 35205527
... A215: 33 | B215: La Normandina | C215: TS | D215: DISCUTIBLE | E215: 70000000 | F215: 77345344
B216: TOTAL 33 CLIENTES QUE ENTRAN | E216: =SUM(E183:E215) | F216: =SUM(F183:F215)
A218: ESCENARIO 3 - CLIENTES QUE SE PIERDEN (ZBB + Trade Spend - presupuesto total)
A219: Prioridad | B219: Cliente / PDV | C219: Bolsa | D219: Tier | E219: Monto FEE Actual | F219: Criterio 3 - Punto medio
A220: 34 | B220: Brothers | C220: ZBB | D220: DISCUTIBLE | E220: 65000000 | F220: 91944874
A221: 35 | B221: Camping Americano | C221: ZBB | D221: DISCUTIBLE | E221: 11000000 | F221: 15559902
A222: 36 | B222: Mambrú | C222: ZBB | D222: DISCUTIBLE | E222: 8000000 | F222: 11265769
A223: 37 | B223: El Condor | C223: TS | D223: DISCUTIBLE | E223: 2200000 | F223: 2430853.7
A224: 38 | B224: Olivo | C224: TS | D224: DISCUTIBLE | E224: 1800000 | F224: 1988880.3
A225: 39 | B225: NEREA | C225: ZBB | D225: DISCUTIBLE | E225: 1700000 | F225: 2404712.1
A226: 40 | B226: El Taino | C226: TS | D226: DISCUTIBLE | E226: 1200000 | F226: 1325920.2
A227: 41 | B227: Lo de Fran | C227: ZBB | D227: DISCUTIBLE | E227: 21000000 | F227: 30553932
A228: 42 | B228: El Bar | C228: TS | D228: DISCUTIBLE | E228: 20000000 | F228: 22098670
A229: 43 | B229: Espacio Pueyrredón | C229: TS | D229: DISCUTIBLE | E229: 17000000 | F229: 18518040
A230: 44 | B230: Honu Beach | C230: TS | D230: DISCUTIBLE | E230: 15000000 | F230: 16875000
A231: 45 | B231: mama Concert | C231: ZBB | D231: DISCUTIBLE | E231: 15000000 | F231: 46693266
... A261: 75 | B261: Balneario 2 Alaciel | C261: TS | D261: DISCUTIBLE | E261: 1300000 | F261: 1443347.9
B262: TOTAL 42 CLIENTES QUE SE PIERDEN | E262: =SUM(E220:E261) | F262: =SUM(F220:F261)
