Workbook

Sheet PARAMETROS
A1: RENOVACION DE CONTRATOS FEE 2026 - PARAMETROS Y SUPUESTOS
A2: Universo de analisis: 76 contratos FEE (2026), unicamente bolsa ZBB (30 contratos)
A4: BOLSAS DE PRESUPUESTO (referencia, archivo original)
A5: Total pagado bolsa ZBB (2026, 30 contratos) | B5: 1101000000 | C5: Dato provisto por el usuario y verificado contra el archivo FEE_2026.xlsx (SUMIF ZBB/TS=ZBB) = coincide exacto.
A6: Total pagado bolsa Trade Spend (2026, 46 contratos) - fuera de alcance | B6: 679000000 | C6: No forma parte de los escenarios (se pidio trabajar solo con ZBB). Se deja como referencia.
A8: ESCENARIOS DE PRESUPUESTO DISPONIBLE (bolsa ZBB)
A9: Escenario 1 - Presupuesto disponible hoy (misma bolsa ZBB) | B9: 1430276270 | C9: Dato provisto por el usuario.
A10: Escenario 2 - Adicional a conseguir | B10: 250000000 | C10: Dato provisto por el usuario.
A11: Escenario 2 - Total teorico (Esc.1 + Adicional) | B11: =$B$9+B10 | C11: Calculado. OJO: el usuario menciono "1.650.000.000 totales", pero 1.430.276.270 + 250.000.000 = 1.680.276.270. Hay una diferencia de $30.276.270 a confirmar.
A12: Escenario 2 - Total CONFIRMADO a usar en el modelo | B12: 1650000000 | C12: VALOR USADO EN EL MODELO (celda editable). Ajustar si el numero correcto es 1.680.276.270 u otro.
A13: Escenario 3 - Presupuesto total disponible | B13: 2000000000 | C13: Dato provisto por el usuario.
A15: TABLA DE INFLACION ACUMULADA POR DURACION (fuente: hoja Hoja5 del archivo original)
A16: Duracion contrato (meses) | B16: Inflacion acumulada
A17: 12 | B17: 0.25
A18: 24 | B18: 0.68
A19: 36 | B19: 2.13
A20: Nota | C20: Para contratos con duracion intermedia (10, 21 meses), el archivo original aplico manualmente la tasa del tramo mas cercano (10m -> tasa de 12m; 21m -> tasa de 24m). Se replico igual criterio.
A22: CRITERIOS DE COSTO DE RENOVACION
A23: Criterio 1 - FEE Actualizado | C23: Valor de referencia de mercado/sistema tomado del archivo original (columna "FEE ACTUALIZADO", hoja BASE CON PAUTA). Se trae como dato fijo porque su formula original enlazaba a un archivo externo no disponible.
A24: Criterio 2 - FEE + Inflacion acumulada | C24: Formula: Monto FEE actual x (1 + Inflacion acumulada segun duracion). Reconstruido como formula viva en la hoja BASE ZBB.
A26: PRIORIZACION Y ALCANCE
A27: 1) Los 30 contratos ZBB se ordenan por Tier (IMPERDIBLE > DISCUTIBLE > CERRO) y, dentro de cada tier, por Monto FEE actual descendente (proxy de importancia por defecto).
A28: 2) La columna "Prioridad" (hoja BASE ZBB) es editable: para cambiar el orden manual, escribir el numero de prioridad deseado y luego reordenar las filas (Datos > Ordenar por columna Prioridad) para que las columnas de acumulado se recalculen correctamente.
A29: 3) El tier "CERRO" corresponde a locales que cierran / cambian de dueño y NO renuevan: se excluyen automaticamente de los 3 escenarios, sin consumir presupuesto (1 contrato: Helena Beach, $110.000.000).
A30: 4) "Cliente" = cada fila / punto de venta (Nombre de Fantasia), ya que cada uno tiene contrato y fee propios. Un mismo Razon Social/Distribuidor puede tener varios clientes (ej. COMERCIAL DEL MAR SA).
A32: ALERTAS DE CALIDAD DE DATO (revisar antes de presentar)
A33: Helena Beach (COMERCIAL DEL MAR SA) | C33: Codigo cliente = "CERRO CAMBIA DE DUEÑOS Y FORMATO" y tier=CERRO. Ademas, el "FEE ACTUALIZADO" (Criterio 1) del archivo original vino en $0 (formula rota / sin dato de origen). Se dejo en $0 y el contrato queda excluido de todas formas por ser CERRO.
A34: Casa Pampa (COMERCIAL DEL MAR SA) | C34: Codigo cliente = "CERRO CAMBIA DE FORMATO PARA SER CALAMAR LOCO HOSTELS" pero el tier de ventas es IMPERDIBLE (cambia de formato/marca pero continuaria). Confirmar si corresponde mantenerlo como renovable.
A35: Negroni Helena (BEBIDAS DEL MAR S.A.) | C35: Codigo cliente = "CERRO" y el comentario dice explicitamente "No renueva; cerro", pero el tier de ventas quedo como IMPERDIBLE. Contradiccion a resolver: hoy el modelo lo trata como IMPERDIBLE (se mantiene en el ranking). Si en la realidad no va a renovar, recomendamos pasarlo a tier CERRO.
A36: El Descorche (BEER TAN S.A.) | C36: Comentario: "Renueva sin fee; no tiene volumen significativo y no esta en LOL". Podria no requerir presupuesto para renovarse (fee=0). Se mantuvo con su Monto FEE actual por consistencia; ajustar si corresponde.

Sheet BASE ZBB
A1: Prioridad | B1: Tier Base | C1: Alerta | D1: Codigo Cliente | E1: Cliente / PDV (Nombre de Fantasia) | F1: Razon Social (Distribuidor) | G1: Marca | H1: Rubro | I1: Vigencia Desde | J1: Vigencia Hasta | K1: Duracion (meses) | L1: Comentario original | M1: Monto FEE Actual (pagado) | N1: % Inflacion acumulada aplicable | O1: Criterio 1 - FEE Actualizado (mercado) | P1: Criterio 2 - FEE + Inflacion | Q1: Diferencia C2 vs C1 ($) | R1: Diferencia C2 vs C1 (%) | S1: Acumulado Criterio 1 | T1: Acumulado Criterio 2 | U1: Escenario 1 - Entra (C1) | V1: Escenario 1 - Entra (C2) | W1: Escenario 2 - Entra (C1) | X1: Escenario 2 - Entra (C2) | Y1: Escenario 3 - Entra (C1) | Z1: Escenario 3 - Entra (C2)
A2: 1 | B2: IMPERDIBLE | D2: 60743 | E2: Mr Jones | F2: Playa Bacana SA | G2: Budweiser | H2: NOCTURNIDAD/EVENTOS | I2: 45658 | J2: 46388 | K2: 24 | L2: Vence post 2026; charlar mas adelante | M2: 170000000 | N2: 0.68 | O2: 1.9319517e+08 | P2: =M2*(1+N2) | Q2: =P2-O2 | R2: =IF(O2=0,"",P2/O2-1) | S2: =IF(B2="CERRO",0,O2) | T2: =IF(B2="CERRO",0,P2) | U2: =IF(B2="CERRO","NO APLICA",IF(S2<=PARAMETROS!$B$9,"SI","NO")) | V2: =IF(B2="CERRO","NO APLICA",IF(T2<=PARAMETROS!$B$9,"SI","NO")) | W2: =IF(B2="CERRO","NO APLICA",IF(S2<=PARAMETROS!$B$12,"SI","NO")) | X2: =IF(B2="CERRO","NO APLICA",IF(T2<=PARAMETROS!$B$12,"SI","NO")) | Y2: =IF(B2="CERRO","NO APLICA",IF(S2<=PARAMETROS!$B$13,"SI","NO")) | Z2: =IF(B2="CERRO","NO APLICA",IF(T2<=PARAMETROS!$B$13,"SI","NO"))
A3: 2 | B3: IMPERDIBLE | D3: 60635 | E3: Quba | F3: Purasal SRL | G3: Budweiser | H3: NOCTURNIDAD/EVENTOS | I3: 45658 | J3: 46388 | K3: 24 | L3: Vence post 2026; charlar mas adelante | M3: 160000000 | N3: 0.68 | O3: 1.8183075e+08 | P3: =M3*(1+N3) | Q3: =P3-O3 | R3: =IF(O3=0,"",P3/O3-1) | S3: =IF(B3="CERRO",S2,S2+O3) | T3: =IF(B3="CERRO",T2,T2+P3) | U3: =IF(B3="CERRO","NO APLICA",IF(S3<=PARAMETROS!$B$9,"SI","NO")) | V3: =IF(B3="CERRO","NO APLICA",IF(T3<=PARAMETROS!$B$9,"SI","NO")) | W3: =IF(B3="CERRO","NO APLICA",IF(S3<=PARAMETROS!$B$12,"SI","NO")) | X3: =IF(B3="CERRO","NO APLICA",IF(T3<=PARAMETROS!$B$12,"SI","NO")) | Y3: =IF(B3="CERRO","NO APLICA",IF(S3<=PARAMETROS!$B$13,"SI","NO")) | Z3: =IF(B3="CERRO","NO APLICA",IF(T3<=PARAMETROS!$B$13,"SI","NO"))
A4: 3 | B4: IMPERDIBLE | D4: 1358 | E4: Tante-Masse-La cabrera | F4: Premium s.a | G4: Stella Artois | H4: GASTRONOMIA | I4: 45658 | J4: 46388 | K4: 24 | L4: Vence post 2026; charlar mas adelante | M4: 140000000 | N4: 0.68 | O4: 1.5910191e+08 | P4: =M4*(1+N4) | Q4: =P4-O4 | R4: =IF(O4=0,"",P4/O4-1) | S4: =IF(B4="CERRO",S3,S3+O4) | T4: =IF(B4="CERRO",T3,T3+P4) | U4: =IF(B4="CERRO","NO APLICA",IF(S4<=PARAMETROS!$B$9,"SI","NO")) | V4: =IF(B4="CERRO","NO APLICA",IF(T4<=PARAMETROS!$B$9,"SI","NO")) | W4: =IF(B4="CERRO","NO APLICA",IF(S4<=PARAMETROS!$B$12,"SI","NO")) | X4: =IF(B4="CERRO","NO APLICA",IF(T4<=PARAMETROS!$B$12,"SI","NO")) | Y4: =IF(B4="CERRO","NO APLICA",IF(S4<=PARAMETROS!$B$13,"SI","NO")) | Z4: =IF(B4="CERRO","NO APLICA",IF(T4<=PARAMETROS!$B$13,"SI","NO"))
A5: 4 | B5: IMPERDIBLE | D5: 60834 | E5: Bruto | F5: Distribución Monkey SA | G5: Budweiser | H5: NOCTURNIDAD/EVENTOS | I5: 45292 | J5: 46388 | K5: 36 | L5: Vence post 2026; charlar mas adelante | M5: 95000000 | N5: 2.13 | O5: 3.133714e+08 | P5: =M5*(1+N5) | Q5: =P5-O5 | R5: =IF(O5=0,"",P5/O5-1) | S5: =IF(B5="CERRO",S4,S4+O5) | T5: =IF(B5="CERRO",T4,T4+P5) | U5: =IF(B5="CERRO","NO APLICA",IF(S5<=PARAMETROS!$B$9,"SI","NO")) | V5: =IF(B5="CERRO","NO APLICA",IF(T5<=PARAMETROS!$B$9,"SI","NO")) | W5: =IF(B5="CERRO","NO APLICA",IF(S5<=PARAMETROS!$B$12,"SI","NO")) | X5: =IF(B5="CERRO","NO APLICA",IF(T5<=PARAMETROS!$B$12,"SI","NO")) | Y5: =IF(B5="CERRO","NO APLICA",IF(S5<=PARAMETROS!$B$13,"SI","NO")) | Z5: =IF(B5="CERRO","NO APLICA",IF(T5<=PARAMETROS!$B$13,"SI","NO"))
A6: 5 | B6: IMPERDIBLE | D6: 62866 | E6: Samsara | F6: Sunny Beach SA | G6: Brahma | H6: NOCTURNIDAD/EVENTOS | I6: 45658 | J6: 46388 | K6: 24 | L6: Vence post 2026; charlar mas adelante | M6: 75000000 | N6: 0.68 | O6: 85233164 | P6: =M6*(1+N6) | Q6: =P6-O6 | R6: =IF(O6=0,"",P6/O6-1) | S6: =IF(B6="CERRO",S5,S5+O6) | T6: =IF(B6="CERRO",T5,T5+P6) | U6: =IF(B6="CERRO","NO APLICA",IF(S6<=PARAMETROS!$B$9,"SI","NO")) | V6: =IF(B6="CERRO","NO APLICA",IF(T6<=PARAMETROS!$B$9,"SI","NO")) | W6: =IF(B6="CERRO","NO APLICA",IF(S6<=PARAMETROS!$B$12,"SI","NO")) | X6: =IF(B6="CERRO","NO APLICA",IF(T6<=PARAMETROS!$B$12,"SI","NO")) | Y6: =IF(B6="CERRO","NO APLICA",IF(S6<=PARAMETROS!$B$13,"SI","NO")) | Z6: =IF(B6="CERRO","NO APLICA",IF(T6<=PARAMETROS!$B$13,"SI","NO"))
A7: 6 | B7: IMPERDIBLE | D7: 3238 | E7: Brothers | F7: Diego Heter | G7: Patagonia | H7: NOCTURNIDAD/EVENTOS | I7: 45627 | J7: 46357 | K7: 24 | L7: Pendiente de revisar con región | M7: 65000000 | N7: 0.68 | O7: 74689748 | P7: =M7*(1+N7) | Q7: =P7-O7 | R7: =IF(O7=0,"",P7/O7-1) | S7: =IF(B7="CERRO",S6,S6+O7) | T7: =IF(B7="CERRO",T6,T6+P7) | U7: =IF(B7="CERRO","NO APLICA",IF(S7<=PARAMETROS!$B$9,"SI","NO")) | V7: =IF(B7="CERRO","NO APLICA",IF(T7<=PARAMETROS!$B$9,"SI","NO")) | W7: =IF(B7="CERRO","NO APLICA",IF(S7<=PARAMETROS!$B$12,"SI","NO")) | X7: =IF(B7="CERRO","NO APLICA",IF(T7<=PARAMETROS!$B$12,"SI","NO")) | Y7: =IF(B7="CERRO","NO APLICA",IF(S7<=PARAMETROS!$B$13,"SI","NO")) | Z7: =IF(B7="CERRO","NO APLICA",IF(T7<=PARAMETROS!$B$13,"SI","NO"))
A8: 7 | B8: IMPERDIBLE | D8: 0 | E8: La Gamba | F8: Eras comercializaciones S.R.L | G8: Stella Artois | H8: BALNEARIOS | I8: 45658 | J8: 46388 | K8: 24 | L8: Vence post 2026; charlar mas adelante | M8: 60000000 | N8: 0.68 | O8: 68186531 | P8: =M8*(1+N8) | Q8: =P8-O8 | R8: =IF(O8=0,"",P8/O8-1) | S8: =IF(B8="CERRO",S7,S7+O8) | T8: =IF(B8="CERRO",T7,T7+P8) | U8: =IF(B8="CERRO","NO APLICA",IF(S8<=PARAMETROS!$B$9,"SI","NO")) | V8: =IF(B8="CERRO","NO APLICA",IF(T8<=PARAMETROS!$B$9,"SI","NO")) | W8: =IF(B8="CERRO","NO APLICA",IF(S8<=PARAMETROS!$B$12,"SI","NO")) | X8: =IF(B8="CERRO","NO APLICA",IF(T8<=PARAMETROS!$B$12,"SI","NO")) | Y8: =IF(B8="CERRO","NO APLICA",IF(S8<=PARAMETROS!$B$13,"SI","NO")) | Z8: =IF(B8="CERRO","NO APLICA",IF(T8<=PARAMETROS!$B$13,"SI","NO"))
A9: 8 | B9: IMPERDIBLE | C9: Codigo de cliente dice CERRO (cambia de formato) pero tier=IMPERDIBLE. Confirmar. | D9: CERRO CAMBIA DE FORMATO PARA SER CALAMAR LOCO HOSTELS | E9: Casa Pampa | F9: SANTIAGO DE COMPOSTELA 1943 S.A. | G9: Stella Artois | H9: GASTRONOMIA | I9: 45658 | J9: 46388 | K9: 24 | L9: Vence post 2026; charlar mas adelante | M9: 25000000 | N9: 0.68 | O9: 28411055 | P9: =M9*(1+N9) | Q9: =P9-O9 | R9: =IF(O9=0,"",P9/O9-1) | S9: =IF(B9="CERRO",S8,S8+O9) | T9: =IF(B9="CERRO",T8,T8+P9) | U9: =IF(B9="CERRO","NO APLICA",IF(S9<=PARAMETROS!$B$9,"SI","NO")) | V9: =IF(B9="CERRO","NO APLICA",IF(T9<=PARAMETROS!$B$9,"SI","NO")) | W9: =IF(B9="CERRO","NO APLICA",IF(S9<=PARAMETROS!$B$12,"SI","NO")) | X9: =IF(B9="CERRO","NO APLICA",IF(T9<=PARAMETROS!$B$12,"SI","NO")) | Y9: =IF(B9="CERRO","NO APLICA",IF(S9<=PARAMETROS!$B$13,"SI","NO")) | Z9: =IF(B9="CERRO","NO APLICA",IF(T9<=PARAMETROS!$B$13,"SI","NO"))
A10: 9 | B10: IMPERDIBLE | D10: 60973 | E10: ESTACION CENTRAL | F10: VAMOELPACK MDP S.A. | G10: Corona | H10: NOCTURNIDAD/EVENTOS | I10: 45292 | J10: 46388 | K10: 36 | L10: Vence post 2026; charlar mas adelante | M10: 25000000 | N10: 2.13 | O10: 56076988 | P10: =M10*(1+N10) | Q10: =P10-O10 | R10: =IF(O10=0,"",P10/O10-1) | S10: =IF(B10="CERRO",S9,S9+O10) | T10: =IF(B10="CERRO",T9,T9+P10) | U10: =IF(B10="CERRO","NO APLICA",IF(S10<=PARAMETROS!$B$9,"SI","NO")) | V10: =IF(B10="CERRO","NO APLICA",IF(T10<=PARAMETROS!$B$9,"SI","NO")) | W10: =IF(B10="CERRO","NO APLICA",IF(S10<=PARAMETROS!$B$12,"SI","NO")) | X10: =IF(B10="CERRO","NO APLICA",IF(T10<=PARAMETROS!$B$12,"SI","NO")) | Y10: =IF(B10="CERRO","NO APLICA",IF(S10<=PARAMETROS!$B$13,"SI","NO")) | Z10: =IF(B10="CERRO","NO APLICA",IF(T10<=PARAMETROS!$B$13,"SI","NO"))
A11: 10 | B11: IMPERDIBLE | D11: 60917 | E11: LOS TOLDOS VIEJOS | F11: COUNTRY GRILLS S. R. L. | G11: Stella Artois | H11: GASTRONOMIA | I11: 45658 | J11: 46388 | K11: 24 | L11: Vence post 2026; charlar mas adelante | M11: 16000000 | N11: 0.68 | O11: 18183075 | P11: =M11*(1+N11) | Q11: =P11-O11 | R11: =IF(O11=0,"",P11/O11-1) | S11: =IF(B11="CERRO",S10,S10+O11) | T11: =IF(B11="CERRO",T10,T10+P11) | U11: =IF(B11="CERRO","NO APLICA",IF(S11<=PARAMETROS!$B$9,"SI","NO")) | V11: =IF(B11="CERRO","NO APLICA",IF(T11<=PARAMETROS!$B$9,"SI","NO")) | W11: =IF(B11="CERRO","NO APLICA",IF(S11<=PARAMETROS!$B$12,"SI","NO")) | X11: =IF(B11="CERRO","NO APLICA",IF(T11<=PARAMETROS!$B$12,"SI","NO")) | Y11: =IF(B11="CERRO","NO APLICA",IF(S11<=PARAMETROS!$B$13,"SI","NO")) | Z11: =IF(B11="CERRO","NO APLICA",IF(T11<=PARAMETROS!$B$13,"SI","NO"))
A12: 11 | B12: IMPERDIBLE | D12: 62431 | E12: Villa Aluminé | F12: Villa Aluminé SA | G12: Stella Artois | H12: NOCTURNIDAD/EVENTOS | I12: 45658 | J12: 46388 | K12: 24 | L12: Vence post 2026; charlar mas adelante | M12: 16000000 | N12: 0.68 | O12: 18183075 | P12: =M12*(1+N12) | Q12: =P12-O12 | R12: =IF(O12=0,"",P12/O12-1) | S12: =IF(B12="CERRO",S11,S11+O12) | T12: =IF(B12="CERRO",T11,T11+P12) | U12: =IF(B12="CERRO","NO APLICA",IF(S12<=PARAMETROS!$B$9,"SI","NO")) | V12: =IF(B12="CERRO","NO APLICA",IF(T12<=PARAMETROS!$B$9,"SI","NO")) | W12: =IF(B12="CERRO","NO APLICA",IF(S12<=PARAMETROS!$B$12,"SI","NO")) | X12: =IF(B12="CERRO","NO APLICA",IF(T12<=PARAMETROS!$B$12,"SI","NO")) | Y12: =IF(B12="CERRO","NO APLICA",IF(S12<=PARAMETROS!$B$13,"SI","NO")) | Z12: =IF(B12="CERRO","NO APLICA",IF(T12<=PARAMETROS!$B$13,"SI","NO"))
A13: 12 | B13: IMPERDIBLE | D13: 8383 | E13: Camping Americano | F13: EPICURAE AMERICANOSERV S.A | G13: Corona | H13: OTROS | I13: 45627 | J13: 46357 | K13: 24 | L13: Pendiente de revisar con región | M13: 11000000 | N13: 0.68 | O13: 12639804 | P13: =M13*(1+N13) | Q13: =P13-O13 | R13: =IF(O13=0,"",P13/O13-1) | S13: =IF(B13="CERRO",S12,S12+O13) | T13: =IF(B13="CERRO",T12,T12+P13) | U13: =IF(B13="CERRO","NO APLICA",IF(S13<=PARAMETROS!$B$9,"SI","NO")) | V13: =IF(B13="CERRO","NO APLICA",IF(T13<=PARAMETROS!$B$9,"SI","NO")) | W13: =IF(B13="CERRO","NO APLICA",IF(S13<=PARAMETROS!$B$12,"SI","NO")) | X13: =IF(B13="CERRO","NO APLICA",IF(T13<=PARAMETROS!$B$12,"SI","NO")) | Y13: =IF(B13="CERRO","NO APLICA",IF(S13<=PARAMETROS!$B$13,"SI","NO")) | Z13: =IF(B13="CERRO","NO APLICA",IF(T13<=PARAMETROS!$B$13,"SI","NO"))
A14: 13 | B14: IMPERDIBLE | D14: 60962 | E14: Cava Federal | F14: Jiro MDQ SA | G14: Stella Artois | H14: NOCTURNIDAD/EVENTOS | I14: 45597 | J14: 46327 | K14: 24 | L14: Renueva; | M14: 10000000 | N14: 0.68 | O14: 11754067 | P14: =M14*(1+N14) | Q14: =P14-O14 | R14: =IF(O14=0,"",P14/O14-1) | S14: =IF(B14="CERRO",S13,S13+O14) | T14: =IF(B14="CERRO",T13,T13+P14) | U14: =IF(B14="CERRO","NO APLICA",IF(S14<=PARAMETROS!$B$9,"SI","NO")) | V14: =IF(B14="CERRO","NO APLICA",IF(T14<=PARAMETROS!$B$9,"SI","NO")) | W14: =IF(B14="CERRO","NO APLICA",IF(S14<=PARAMETROS!$B$12,"SI","NO")) | X14: =IF(B14="CERRO","NO APLICA",IF(T14<=PARAMETROS!$B$12,"SI","NO")) | Y14: =IF(B14="CERRO","NO APLICA",IF(S14<=PARAMETROS!$B$13,"SI","NO")) | Z14: =IF(B14="CERRO","NO APLICA",IF(T14<=PARAMETROS!$B$13,"SI","NO"))
A15: 14 | B15: IMPERDIBLE | D15: 8242 | E15: Palma Bristo Amarras | F15: Morosenlacosta | G15: Corona | H15: BALNEARIOS | I15: 45292 | J15: 46388 | K15: 36 | L15: Vence post 2026; charlar mas adelante | M15: 10000000 | N15: 2.13 | O15: 22430795 | P15: =M15*(1+N15) | Q15: =P15-O15 | R15: =IF(O15=0,"",P15/O15-1) | S15: =IF(B15="CERRO",S14,S14+O15) | T15: =IF(B15="CERRO",T14,T14+P15) | U15: =IF(B15="CERRO","NO APLICA",IF(S15<=PARAMETROS!$B$9,"SI","NO")) | V15: =IF(B15="CERRO","NO APLICA",IF(T15<=PARAMETROS!$B$9,"SI","NO")) | W15: =IF(B15="CERRO","NO APLICA",IF(S15<=PARAMETROS!$B$12,"SI","NO")) | X15: =IF(B15="CERRO","NO APLICA",IF(T15<=PARAMETROS!$B$12,"SI","NO")) | Y15: =IF(B15="CERRO","NO APLICA",IF(S15<=PARAMETROS!$B$13,"SI","NO")) | Z15: =IF(B15="CERRO","NO APLICA",IF(T15<=PARAMETROS!$B$13,"SI","NO"))
A16: 15 | B16: IMPERDIBLE | D16: 60931 | E16: Mambrú | F16: BALL LLATINAS FERNANDO JORGE | G16: Quilmes | H16: GASTRONOMIA | I16: 45658 | J16: 46388 | K16: 24 | L16: Vence post 2026; charlar mas adelante | M16: 8000000 | N16: 0.68 | O16: 9091537.5 | P16: =M16*(1+N16) | Q16: =P16-O16 | R16: =IF(O16=0,"",P16/O16-1) | S16: =IF(B16="CERRO",S15,S15+O16) | T16: =IF(B16="CERRO",T15,T15+P16) | U16: =IF(B16="CERRO","NO APLICA",IF(S16<=PARAMETROS!$B$9,"SI","NO")) | V16: =IF(B16="CERRO","NO APLICA",IF(T16<=PARAMETROS!$B$9,"SI","NO")) | W16: =IF(B16="CERRO","NO APLICA",IF(S16<=PARAMETROS!$B$12,"SI","NO")) | X16: =IF(B16="CERRO","NO APLICA",IF(T16<=PARAMETROS!$B$12,"SI","NO")) | Y16: =IF(B16="CERRO","NO APLICA",IF(S16<=PARAMETROS!$B$13,"SI","NO")) | Z16: =IF(B16="CERRO","NO APLICA",IF(T16<=PARAMETROS!$B$13,"SI","NO"))
A17: 16 | B17: IMPERDIBLE | D17: 4967 | E17: Mattone | F17: Bunge y Mar SA | G17: Stella Artois | H17: GASTRONOMIA | I17: 45658 | J17: 46388 | K17: 24 | L17: Vence post 2026; charlar mas adelante | M17: 6000000 | N17: 0.68 | O17: 6818653.1 | P17: =M17*(1+N17) | Q17: =P17-O17 | R17: =IF(O17=0,"",P17/O17-1) | S17: =IF(B17="CERRO",S16,S16+O17) | T17: =IF(B17="CERRO",T16,T16+P17) | U17: =IF(B17="CERRO","NO APLICA",IF(S17<=PARAMETROS!$B$9,"SI","NO")) | V17: =IF(B17="CERRO","NO APLICA",IF(T17<=PARAMETROS!$B$9,"SI","NO")) | W17: =IF(B17="CERRO","NO APLICA",IF(S17<=PARAMETROS!$B$12,"SI","NO")) | X17: =IF(B17="CERRO","NO APLICA",IF(T17<=PARAMETROS!$B$12,"SI","NO")) | Y17: =IF(B17="CERRO","NO APLICA",IF(S17<=PARAMETROS!$B$13,"SI","NO")) | Z17: =IF(B17="CERRO","NO APLICA",IF(T17<=PARAMETROS!$B$13,"SI","NO"))
A18: 17 | B18: IMPERDIBLE | D18: 60753 | E18: DOS 55 | F18: Huergo Roberto Adrián | G18: Stella Artois | H18: GASTRONOMIA | I18: 45778 | J18: 46143 | K18: 12 | L18: Renueva; importante para visitas | M18: 5000000 | N18: 0.25 | O18: 5243042.5 | P18: =M18*(1+N18) | Q18: =P18-O18 | R18: =IF(O18=0,"",P18/O18-1) | S18: =IF(B18="CERRO",S17,S17+O18) | T18: =IF(B18="CERRO",T17,T17+P18) | U18: =IF(B18="CERRO","NO APLICA",IF(S18<=PARAMETROS!$B$9,"SI","NO")) | V18: =IF(B18="CERRO","NO APLICA",IF(T18<=PARAMETROS!$B$9,"SI","NO")) | W18: =IF(B18="CERRO","NO APLICA",IF(S18<=PARAMETROS!$B$12,"SI","NO")) | X18: =IF(B18="CERRO","NO APLICA",IF(T18<=PARAMETROS!$B$12,"SI","NO")) | Y18: =IF(B18="CERRO","NO APLICA",IF(S18<=PARAMETROS!$B$13,"SI","NO")) | Z18: =IF(B18="CERRO","NO APLICA",IF(T18<=PARAMETROS!$B$13,"SI","NO"))
A19: 18 | B19: IMPERDIBLE | D19: 60356 | E19: SANTA | F19: Praisolo SA | G19: Stella Artois | H19: BALNEARIOS | I19: 45292 | J19: 46388 | K19: 36 | L19: Vence post 2026; charlar mas adelante | M19: 5000000 | N19: 2.13 | O19: 11215398 | P19: =M19*(1+N19) | Q19: =P19-O19 | R19: =IF(O19=0,"",P19/O19-1) | S19: =IF(B19="CERRO",S18,S18+O19) | T19: =IF(B19="CERRO",T18,T18+P19) | U19: =IF(B19="CERRO","NO APLICA",IF(S19<=PARAMETROS!$B$9,"SI","NO")) | V19: =IF(B19="CERRO","NO APLICA",IF(T19<=PARAMETROS!$B$9,"SI","NO")) | W19: =IF(B19="CERRO","NO APLICA",IF(S19<=PARAMETROS!$B$12,"SI","NO")) | X19: =IF(B19="CERRO","NO APLICA",IF(T19<=PARAMETROS!$B$12,"SI","NO")) | Y19: =IF(B19="CERRO","NO APLICA",IF(S19<=PARAMETROS!$B$13,"SI","NO")) | Z19: =IF(B19="CERRO","NO APLICA",IF(T19<=PARAMETROS!$B$13,"SI","NO"))
A20: 19 | B20: IMPERDIBLE | D20: 8545 | E20: Hondo | F20: De Jesús Juan Aramis | G20: Stella Artois | H20: GASTRONOMIA | I20: 45627 | J20: 46357 | K20: 24 | L20: Pendiente de revisar con región | M20: 4000000 | N20: 0.68 | O20: 4596292.2 | P20: =M20*(1+N20) | Q20: =P20-O20 | R20: =IF(O20=0,"",P20/O20-1) | S20: =IF(B20="CERRO",S19,S19+O20) | T20: =IF(B20="CERRO",T19,T19+P20) | U20: =IF(B20="CERRO","NO APLICA",IF(S20<=PARAMETROS!$B$9,"SI","NO")) | V20: =IF(B20="CERRO","NO APLICA",IF(T20<=PARAMETROS!$B$9,"SI","NO")) | W20: =IF(B20="CERRO","NO APLICA",IF(S20<=PARAMETROS!$B$12,"SI","NO")) | X20: =IF(B20="CERRO","NO APLICA",IF(T20<=PARAMETROS!$B$12,"SI","NO")) | Y20: =IF(B20="CERRO","NO APLICA",IF(S20<=PARAMETROS!$B$13,"SI","NO")) | Z20: =IF(B20="CERRO","NO APLICA",IF(T20<=PARAMETROS!$B$13,"SI","NO"))
A21: 20 | B21: IMPERDIBLE | C21: Comentario dice "No renueva; cerro" pero tier=IMPERDIBLE. Contradiccion a resolver. | D21: CERRO | E21: Negroni Helena | F21: LOJAPAZ PINAMAR S.A. | G21: Stella Artois | H21: BALNEARIOS | I21: 45597 | J21: 46327 | K21: 24 | L21: No renueva; cerro | M21: 4000000 | N21: 0.68 | O21: 4701626.7 | P21: =M21*(1+N21) | Q21: =P21-O21 | R21: =IF(O21=0,"",P21/O21-1) | S21: =IF(B21="CERRO",S20,S20+O21) | T21: =IF(B21="CERRO",T20,T20+P21) | U21: =IF(B21="CERRO","NO APLICA",IF(S21<=PARAMETROS!$B$9,"SI","NO")) | V21: =IF(B21="CERRO","NO APLICA",IF(T21<=PARAMETROS!$B$9,"SI","NO")) | W21: =IF(B21="CERRO","NO APLICA",IF(S21<=PARAMETROS!$B$12,"SI","NO")) | X21: =IF(B21="CERRO","NO APLICA",IF(T21<=PARAMETROS!$B$12,"SI","NO")) | Y21: =IF(B21="CERRO","NO APLICA",IF(S21<=PARAMETROS!$B$13,"SI","NO")) | Z21: =IF(B21="CERRO","NO APLICA",IF(T21<=PARAMETROS!$B$13,"SI","NO"))
A22: 21 | B22: IMPERDIBLE | D22: 5978 | E22: Cooperativa de Pesca | F22: Cooperativa de trabajo artesanal pescadores de Pinamar ltda | G22: Quilmes | H22: GASTRONOMIA | I22: 45658 | J22: 46388 | K22: 24 | L22: Vence post 2026; charlar mas adelante | M22: 3500000 | N22: 0.68 | O22: 4679467.8 | P22: =M22*(1+N22) | Q22: =P22-O22 | R22: =IF(O22=0,"",P22/O22-1) | S22: =IF(B22="CERRO",S21,S21+O22) | T22: =IF(B22="CERRO",T21,T21+P22) | U22: =IF(B22="CERRO","NO APLICA",IF(S22<=PARAMETROS!$B$9,"SI","NO")) | V22: =IF(B22="CERRO","NO APLICA",IF(T22<=PARAMETROS!$B$9,"SI","NO")) | W22: =IF(B22="CERRO","NO APLICA",IF(S22<=PARAMETROS!$B$12,"SI","NO")) | X22: =IF(B22="CERRO","NO APLICA",IF(T22<=PARAMETROS!$B$12,"SI","NO")) | Y22: =IF(B22="CERRO","NO APLICA",IF(S22<=PARAMETROS!$B$13,"SI","NO")) | Z22: =IF(B22="CERRO","NO APLICA",IF(T22<=PARAMETROS!$B$13,"SI","NO"))
A23: 22 | B23: IMPERDIBLE | D23: 61033 | E23: NEREA | F23: SHAW AND BEACH S.A. | G23: Stella Artois | H23: GASTRONOMIA | I23: 45627 | J23: 46357 | K23: 24 | L23: Pendiente de revisar con región | M23: 1700000 | N23: 0.68 | O23: 1953424.2 | P23: =M23*(1+N23) | Q23: =P23-O23 | R23: =IF(O23=0,"",P23/O23-1) | S23: =IF(B23="CERRO",S22,S22+O23) | T23: =IF(B23="CERRO",T22,T22+P23) | U23: =IF(B23="CERRO","NO APLICA",IF(S23<=PARAMETROS!$B$9,"SI","NO")) | V23: =IF(B23="CERRO","NO APLICA",IF(T23<=PARAMETROS!$B$9,"SI","NO")) | W23: =IF(B23="CERRO","NO APLICA",IF(S23<=PARAMETROS!$B$12,"SI","NO")) | X23: =IF(B23="CERRO","NO APLICA",IF(T23<=PARAMETROS!$B$12,"SI","NO")) | Y23: =IF(B23="CERRO","NO APLICA",IF(S23<=PARAMETROS!$B$13,"SI","NO")) | Z23: =IF(B23="CERRO","NO APLICA",IF(T23<=PARAMETROS!$B$13,"SI","NO"))
A24: 23 | B24: DISCUTIBLE | D24: 62691 | E24: Lo de Fran | F24: SALITRE MARINO S. A. | G24: Stella Artois | H24: GASTRONOMIA | I24: 45536 | J24: 46266 | K24: 24 | L24: Renueva; | M24: 21000000 | N24: 0.68 | O24: 25827863 | P24: =M24*(1+N24) | Q24: =P24-O24 | R24: =IF(O24=0,"",P24/O24-1) | S24: =IF(B24="CERRO",S23,S23+O24) | T24: =IF(B24="CERRO",T23,T23+P24) | U24: =IF(B24="CERRO","NO APLICA",IF(S24<=PARAMETROS!$B$9,"SI","NO")) | V24: =IF(B24="CERRO","NO APLICA",IF(T24<=PARAMETROS!$B$9,"SI","NO")) | W24: =IF(B24="CERRO","NO APLICA",IF(S24<=PARAMETROS!$B$12,"SI","NO")) | X24: =IF(B24="CERRO","NO APLICA",IF(T24<=PARAMETROS!$B$12,"SI","NO")) | Y24: =IF(B24="CERRO","NO APLICA",IF(S24<=PARAMETROS!$B$13,"SI","NO")) | Z24: =IF(B24="CERRO","NO APLICA",IF(T24<=PARAMETROS!$B$13,"SI","NO"))
A25: 24 | B25: DISCUTIBLE | D25: 0 | E25: mama Concert | F25: Pinamar S.A | G25: Corona | H25: BALNEARIOS | I25: 45658 | J25: 46388 | K25: 24 | L25: Vence post 2026; charlar mas adelante | M25: 15000000 | N25: 0.68 | O25: 68186531 | P25: =M25*(1+N25) | Q25: =P25-O25 | R25: =IF(O25=0,"",P25/O25-1) | S25: =IF(B25="CERRO",S24,S24+O25) | T25: =IF(B25="CERRO",T24,T24+P25) | U25: =IF(B25="CERRO","NO APLICA",IF(S25<=PARAMETROS!$B$9,"SI","NO")) | V25: =IF(B25="CERRO","NO APLICA",IF(T25<=PARAMETROS!$B$9,"SI","NO")) | W25: =IF(B25="CERRO","NO APLICA",IF(S25<=PARAMETROS!$B$12,"SI","NO")) | X25: =IF(B25="CERRO","NO APLICA",IF(T25<=PARAMETROS!$B$12,"SI","NO")) | Y25: =IF(B25="CERRO","NO APLICA",IF(S25<=PARAMETROS!$B$13,"SI","NO")) | Z25: =IF(B25="CERRO","NO APLICA",IF(T25<=PARAMETROS!$B$13,"SI","NO"))
A26: 25 | B26: DISCUTIBLE | D26: 4822 | E26: Mirador Tandil | F26: GASTRO LLE TANDIL S.A.S | G26: Patagonia | H26: GASTRONOMIA | I26: 45658 | J26: 46388 | K26: 24 | L26: Vence post 2026; charlar mas adelante | M26: 15000000 | N26: 0.68 | O26: 17046633 | P26: =M26*(1+N26) | Q26: =P26-O26 | R26: =IF(O26=0,"",P26/O26-1) | S26: =IF(B26="CERRO",S25,S25+O26) | T26: =IF(B26="CERRO",T25,T25+P26) | U26: =IF(B26="CERRO","NO APLICA",IF(S26<=PARAMETROS!$B$9,"SI","NO")) | V26: =IF(B26="CERRO","NO APLICA",IF(T26<=PARAMETROS!$B$9,"SI","NO")) | W26: =IF(B26="CERRO","NO APLICA",IF(S26<=PARAMETROS!$B$12,"SI","NO")) | X26: =IF(B26="CERRO","NO APLICA",IF(T26<=PARAMETROS!$B$12,"SI","NO")) | Y26: =IF(B26="CERRO","NO APLICA",IF(S26<=PARAMETROS!$B$13,"SI","NO")) | Z26: =IF(B26="CERRO","NO APLICA",IF(T26<=PARAMETROS!$B$13,"SI","NO"))
A27: 26 | B27: DISCUTIBLE | D27: 60832 | E27: Pontevedra/Di Mero/Membrillo/Brasa | F27: PONTEBRAP S. A. | G27: Stella Artois | H27: GASTRONOMIA | I27: 45658 | J27: 46388 | K27: 24 | L27: Vence post 2026; charlar mas adelante | M27: 10000000 | N27: 0.68 | O27: 11364422 | P27: =M27*(1+N27) | Q27: =P27-O27 | R27: =IF(O27=0,"",P27/O27-1) | S27: =IF(B27="CERRO",S26,S26+O27) | T27: =IF(B27="CERRO",T26,T26+P27) | U27: =IF(B27="CERRO","NO APLICA",IF(S27<=PARAMETROS!$B$9,"SI","NO")) | V27: =IF(B27="CERRO","NO APLICA",IF(T27<=PARAMETROS!$B$9,"SI","NO")) | W27: =IF(B27="CERRO","NO APLICA",IF(S27<=PARAMETROS!$B$12,"SI","NO")) | X27: =IF(B27="CERRO","NO APLICA",IF(T27<=PARAMETROS!$B$12,"SI","NO")) | Y27: =IF(B27="CERRO","NO APLICA",IF(S27<=PARAMETROS!$B$13,"SI","NO")) | Z27: =IF(B27="CERRO","NO APLICA",IF(T27<=PARAMETROS!$B$13,"SI","NO"))
A28: 27 | B28: DISCUTIBLE | D28: 62917 | E28: Hamburguesería Weiss | F28: Senno Gabriel | G28: Corona | H28: GASTRONOMIA | I28: 45717 | J28: 46357 | K28: 21 | L28: Pendiente de revisar con región | M28: 6000000 | N28: 0.68 | O28: 6346284.6 | P28: =M28*(1+N28) | Q28: =P28-O28 | R28: =IF(O28=0,"",P28/O28-1) | S28: =IF(B28="CERRO",S27,S27+O28) | T28: =IF(B28="CERRO",T27,T27+P28) | U28: =IF(B28="CERRO","NO APLICA",IF(S28<=PARAMETROS!$B$9,"SI","NO")) | V28: =IF(B28="CERRO","NO APLICA",IF(T28<=PARAMETROS!$B$9,"SI","NO")) | W28: =IF(B28="CERRO","NO APLICA",IF(S28<=PARAMETROS!$B$12,"SI","NO")) | X28: =IF(B28="CERRO","NO APLICA",IF(T28<=PARAMETROS!$B$12,"SI","NO")) | Y28: =IF(B28="CERRO","NO APLICA",IF(S28<=PARAMETROS!$B$13,"SI","NO")) | Z28: =IF(B28="CERRO","NO APLICA",IF(T28<=PARAMETROS!$B$13,"SI","NO"))
A29: 28 | B29: DISCUTIBLE | C29: Comentario indica que renovaria SIN FEE (bajo volumen). Revisar si corresponde presupuesto $0. | D29: 5726 | E29: El Descorche | F29: Titno Rosado y Blanco SA | G29: Patagonia | H29: GASTRONOMIA | I29: 45566 | J29: 46296 | K29: 24 | L29: Renueva sin fee; no tiene volumen significativo y no esta en LOL | M29: 5800000 | N29: 0.68 | O29: 6973594.1 | P29: =M29*(1+N29) | Q29: =P29-O29 | R29: =IF(O29=0,"",P29/O29-1) | S29: =IF(B29="CERRO",S28,S28+O29) | T29: =IF(B29="CERRO",T28,T28+P29) | U29: =IF(B29="CERRO","NO APLICA",IF(S29<=PARAMETROS!$B$9,"SI","NO")) | V29: =IF(B29="CERRO","NO APLICA",IF(T29<=PARAMETROS!$B$9,"SI","NO")) | W29: =IF(B29="CERRO","NO APLICA",IF(S29<=PARAMETROS!$B$12,"SI","NO")) | X29: =IF(B29="CERRO","NO APLICA",IF(T29<=PARAMETROS!$B$12,"SI","NO")) | Y29: =IF(B29="CERRO","NO APLICA",IF(S29<=PARAMETROS!$B$13,"SI","NO")) | Z29: =IF(B29="CERRO","NO APLICA",IF(T29<=PARAMETROS!$B$13,"SI","NO"))
A30: 29 | B30: DISCUTIBLE | D30: 61357 | E30: Alamacén de carnes | F30: MARTIRE MARCOS EMANUEL | G30: Stella Artois | H30: GASTRONOMIA | I30: 45962 | J30: 46327 | K30: 12 | L30: Pendiente de revisar con región | M30: 3000000 | N30: 0.25 | O30: 2943966.6 | P30: =M30*(1+N30) | Q30: =P30-O30 | R30: =IF(O30=0,"",P30/O30-1) | S30: =IF(B30="CERRO",S29,S29+O30) | T30: =IF(B30="CERRO",T29,T29+P30) | U30: =IF(B30="CERRO","NO APLICA",IF(S30<=PARAMETROS!$B$9,"SI","NO")) | V30: =IF(B30="CERRO","NO APLICA",IF(T30<=PARAMETROS!$B$9,"SI","NO")) | W30: =IF(B30="CERRO","NO APLICA",IF(S30<=PARAMETROS!$B$12,"SI","NO")) | X30: =IF(B30="CERRO","NO APLICA",IF(T30<=PARAMETROS!$B$12,"SI","NO")) | Y30: =IF(B30="CERRO","NO APLICA",IF(S30<=PARAMETROS!$B$13,"SI","NO")) | Z30: =IF(B30="CERRO","NO APLICA",IF(T30<=PARAMETROS!$B$13,"SI","NO"))
A31: 30 | B31: CERRO | C31: CERRO real. Criterio 1 sin dato de origen ($0). Excluido de todos los escenarios (no aplica). | D31: CERRO CAMBIA DE DUEÑOS Y FORMATO | E31: Helena Beach | F31: Greco Group | G31: Stella Artois | H31: BALNEARIOS | I31: 45658 | J31: 46388 | K31: 24 | L31: Vence post 2026; charlar mas adelante | M31: 110000000 | N31: 0.68 | O31: 0 | P31: =M31*(1+N31) | Q31: =P31-O31 | R31: =IF(O31=0,"",P31/O31-1) | S31: =IF(B31="CERRO",S30,S30+O31) | T31: =IF(B31="CERRO",T30,T30+P31) | U31: =IF(B31="CERRO","NO APLICA",IF(S31<=PARAMETROS!$B$9,"SI","NO")) | V31: =IF(B31="CERRO","NO APLICA",IF(T31<=PARAMETROS!$B$9,"SI","NO")) | W31: =IF(B31="CERRO","NO APLICA",IF(S31<=PARAMETROS!$B$12,"SI","NO")) | X31: =IF(B31="CERRO","NO APLICA",IF(T31<=PARAMETROS!$B$12,"SI","NO")) | Y31: =IF(B31="CERRO","NO APLICA",IF(S31<=PARAMETROS!$B$13,"SI","NO")) | Z31: =IF(B31="CERRO","NO APLICA",IF(T31<=PARAMETROS!$B$13,"SI","NO"))
L33: TOTAL 30 CONTRATOS ZBB | M33: =SUM(M2:M31) | O33: =SUM(O2:O31) | P33: =SUM(P2:P31)

Sheet RESUMEN ESCENARIOS
A1: RESUMEN DE ESCENARIOS - BOLSA ZBB (30 contratos, $1.101.000.000 pagados hoy)
A2: El contrato CERRO (Helena Beach, $110.000.000) se excluye de los 3 escenarios en todos los casos: no renueva por cierre/cambio de local, no compite por presupuesto.
A4: Escenario | B4: Criterio de costo | C4: Presupuesto disponible | D4: Contratos que entran | E4: Contratos que se pierden | F4: Monto usado | G4: Sobrante / Faltante | H4: Perdidos IMPERDIBLE | I4: Perdidos DISCUTIBLE | J4: Monto FEE actual en riesgo (perdidos)
A5: Escenario 1 | B5: Criterio 1 - FEE Actualizado | C5: =PARAMETROS!$B$9 | D5: =COUNTIF('BASE ZBB'!U2:U31,"SI") | E5: =COUNTIF('BASE ZBB'!U2:U31,"NO") | F5: =SUMIFS('BASE ZBB'!O2:O31,'BASE ZBB'!U2:U31,"SI") | G5: =C5-F5 | H5: =COUNTIFS('BASE ZBB'!U2:U31,"NO",'BASE ZBB'!$B$2:$B$31,"IMPERDIBLE") | I5: =COUNTIFS('BASE ZBB'!U2:U31,"NO",'BASE ZBB'!$B$2:$B$31,"DISCUTIBLE") | J5: =SUMIFS('BASE ZBB'!$M$2:$M$31,'BASE ZBB'!U2:U31,"NO")
A6: Escenario 1 | B6: Criterio 2 - FEE + Inflacion | C6: =PARAMETROS!$B$9 | D6: =COUNTIF('BASE ZBB'!V2:V31,"SI") | E6: =COUNTIF('BASE ZBB'!V2:V31,"NO") | F6: =SUMIFS('BASE ZBB'!P2:P31,'BASE ZBB'!V2:V31,"SI") | G6: =C6-F6 | H6: =COUNTIFS('BASE ZBB'!V2:V31,"NO",'BASE ZBB'!$B$2:$B$31,"IMPERDIBLE") | I6: =COUNTIFS('BASE ZBB'!V2:V31,"NO",'BASE ZBB'!$B$2:$B$31,"DISCUTIBLE") | J6: =SUMIFS('BASE ZBB'!$M$2:$M$31,'BASE ZBB'!V2:V31,"NO")
A8: Escenario 2 | B8: Criterio 1 - FEE Actualizado | C8: =PARAMETROS!$B$12 | D8: =COUNTIF('BASE ZBB'!W2:W31,"SI") | E8: =COUNTIF('BASE ZBB'!W2:W31,"NO") | F8: =SUMIFS('BASE ZBB'!O2:O31,'BASE ZBB'!W2:W31,"SI") | G8: =C8-F8 | H8: =COUNTIFS('BASE ZBB'!W2:W31,"NO",'BASE ZBB'!$B$2:$B$31,"IMPERDIBLE") | I8: =COUNTIFS('BASE ZBB'!W2:W31,"NO",'BASE ZBB'!$B$2:$B$31,"DISCUTIBLE") | J8: =SUMIFS('BASE ZBB'!$M$2:$M$31,'BASE ZBB'!W2:W31,"NO")
A9: Escenario 2 | B9: Criterio 2 - FEE + Inflacion | C9: =PARAMETROS!$B$12 | D9: =COUNTIF('BASE ZBB'!X2:X31,"SI") | E9: =COUNTIF('BASE ZBB'!X2:X31,"NO") | F9: =SUMIFS('BASE ZBB'!P2:P31,'BASE ZBB'!X2:X31,"SI") | G9: =C9-F9 | H9: =COUNTIFS('BASE ZBB'!X2:X31,"NO",'BASE ZBB'!$B$2:$B$31,"IMPERDIBLE") | I9: =COUNTIFS('BASE ZBB'!X2:X31,"NO",'BASE ZBB'!$B$2:$B$31,"DISCUTIBLE") | J9: =SUMIFS('BASE ZBB'!$M$2:$M$31,'BASE ZBB'!X2:X31,"NO")
A11: Escenario 3 | B11: Criterio 1 - FEE Actualizado | C11: =PARAMETROS!$B$13 | D11: =COUNTIF('BASE ZBB'!Y2:Y31,"SI") | E11: =COUNTIF('BASE ZBB'!Y2:Y31,"NO") | F11: =SUMIFS('BASE ZBB'!O2:O31,'BASE ZBB'!Y2:Y31,"SI") | G11: =C11-F11 | H11: =COUNTIFS('BASE ZBB'!Y2:Y31,"NO",'BASE ZBB'!$B$2:$B$31,"IMPERDIBLE") | I11: =COUNTIFS('BASE ZBB'!Y2:Y31,"NO",'BASE ZBB'!$B$2:$B$31,"DISCUTIBLE") | J11: =SUMIFS('BASE ZBB'!$M$2:$M$31,'BASE ZBB'!Y2:Y31,"NO")
A12: Escenario 3 | B12: Criterio 2 - FEE + Inflacion | C12: =PARAMETROS!$B$13 | D12: =COUNTIF('BASE ZBB'!Z2:Z31,"SI") | E12: =COUNTIF('BASE ZBB'!Z2:Z31,"NO") | F12: =SUMIFS('BASE ZBB'!P2:P31,'BASE ZBB'!Z2:Z31,"SI") | G12: =C12-F12 | H12: =COUNTIFS('BASE ZBB'!Z2:Z31,"NO",'BASE ZBB'!$B$2:$B$31,"IMPERDIBLE") | I12: =COUNTIFS('BASE ZBB'!Z2:Z31,"NO",'BASE ZBB'!$B$2:$B$31,"DISCUTIBLE") | J12: =SUMIFS('BASE ZBB'!$M$2:$M$31,'BASE ZBB'!Z2:Z31,"NO")
A14: COMO VER EL LISTADO EXACTO DE CLIENTES QUE SE PIERDEN
A15: En la hoja "BASE ZBB", usar el filtro (encabezado con flecha) de la columna del escenario/criterio que se quiera ver (ej. "Escenario 1 - Entra (C1)") y filtrar por "NO". Las filas visibles son los clientes que se pierden en ese escenario.
